{"timestamp":1753101965461,"data":[{"id":"aefa7500ef2e7b81a175dd14a6602432","sport_key":"americanfootball_nfl_preseason","sport_title":"NFL Preseason","commence_time":"2025-08-01T00:00:00Z","home_team":"Detroit Lions","away_team":"Los Angeles Chargers","bookmakers":[{"key":"draftkings","title":"DraftKings","last_update":"2025-07-21T04:46:30Z","markets":[{"key":"h2h","last_update":"2025-07-21T04:46:30Z","outcomes":[{"name":"Detroit Lions","price":1.89},{"name":"Los Angeles Chargers","price":1.93}]},{"key":"totals","last_update":"2025-07-21T04:46:30Z","outcomes":[{"name":"Over","price":1.91,"point":32.5},{"name":"Under","price":1.91,"point":32.5}]}]},{"key":"gtbets","title":"GTbets","last_update":"2025-07-21T04:46:33Z","markets":[{"key":"h2h","last_update":"2025-07-21T04:46:33Z","outcomes":[{"name":"Detroit Lions","price":1.91},{"name":"Los Angeles Chargers","price":1.91}]},{"key":"totals","last_update":"2025-07-21T04:46:33Z","outcomes":[{"name":"Over","price":1.92,"point":32.5},{"name":"Under","price":1.92,"point":32.5}]}]},{"key":"betonlineag","title":"BetOnline.ag","last_update":"2025-07-21T04:46:30Z","markets":[{"key":"totals","last_update":"2025-07-21T04:46:30Z","outcomes":[{"name":"Over","price":1.91,"point":33},{"name":"Under","price":1.91,"point":33}]}]},{"key":"lowvig","title":"LowVig.ag","last_update":"2025-07-21T04:46:31Z","markets":[{"key":"totals","last_update":"2025-07-21T04:46:31Z","outcomes":[{"name":"Over","price":1.93,"point":33},{"name":"Under","price":1.93,"point":33}]}]},{"key":"betanysports","title":"BetAnySports","last_update":"2025-07-21T04:46:31Z","markets":[{"key":"totals","last_update":"2025-07-21T04:46:30Z","outcomes":[{"name":"Over","price":1.91,"point":33},{"name":"Under","price":1.91,"point":33}]}]},{"key":"onexbet","title":"1xBet","last_update":"2025-07-21T04:46:30Z","markets":[{"key":"totals","last_update":"2025-07-21T04:46:30Z","outcomes":[{"name":"Over","price":1.91,"point":32.5},{"name":"Under","price":1.91,"point":32.5}]}]},{"key":"betsson","title":"Betsson","last_update":"2025-07-21T04:45:40Z","markets":[{"key":"h2h","last_update":"2025-07-21T04:45:40Z","outcomes":[{"name":"Detroit Lions","price":1.88},{"name":"Los Angeles Chargers","price":1.88}]},{"key":"totals","last_update":"2025-07-21T04:45:40Z","outcomes":[{"name":"Over","price":1.84,"point":32.5},{"name":"Under","price":1.92,"point":32.5}]}]},{"key":"nordicbet","title":"Nordic Bet","last_update":"2025-07-21T04:46:06Z","markets":[{"key":"h2h","last_update":"2025-07-21T04:46:06Z","outcomes":[{"name":"Detroit Lions","price":1.88},{"name":"Los Angeles Chargers","price":1.88}]},{"key":"totals","last_update":"2025-07-21T04:46:06Z","outcomes":[{"name":"Over","price":1.84,"point":32.5},{"name":"Under","price":1.92,"point":32.5}]}]},{"key":"paddypower","title":"Paddy Power","last_update":"2025-07-21T04:44:53Z","markets":[{"key":"h2h","last_update":"2025-07-21T04:44:53Z","outcomes":[{"name":"Detroit Lions","price":1.8},{"name":"Los Angeles Chargers","price":1.91}]}]},{"key":"sportsbet","title":"SportsBet","last_update":"2025-07-21T04:45:55Z","markets":[{"key":"h2h","last_update":"2025-07-21T04:45:55Z","outcomes":[{"name":"Detroit Lions","price":1.86},{"name":"Los Angeles Chargers","price":1.95}]},{"key":"totals","last_update":"2025-07-21T04:45:55Z","outcomes":[{"name":"Over","price":1.9,"point":32.5},{"name":"Under","price":1.9,"point":32.5}]}]},{"key":"fanduel","title":"FanDuel","last_update":"2025-07-21T04:44:29Z","markets":[{"key":"h2h","last_update":"2025-07-21T04:44:29Z","outcomes":[{"name":"Detroit Lions","price":1.87},{"name":"Los Angeles Chargers","price":1.95}]},{"key":"totals","last_update":"2025-07-21T04:44:29Z","outcomes":[{"name":"Over","price":1.91,"point":32.5},{"name":"Under","price":1.91,"point":32.5}]}]},{"key":"neds","title":"Neds","last_update":"2025-07-21T04:45:57Z","markets":[{"key":"h2h","last_update":"2025-07-21T04:45:57Z","outcomes":[{"name":"Detroit Lions","price":1.9},{"name":"Los Angeles Chargers","price":1.9}]}]},{"key":"ladbrokes_au","title":"Ladbrokes","last_update":"2025-07-21T04:46:06Z","markets":[{"key":"h2h","last_update":"2025-07-21T04:46:06Z","outcomes":[{"name":"Detroit Lions","price":1.9},{"name":"Los Angeles Chargers","price":1.9}]}]},{"key":"everygame","title":"Everygame","last_update":"2025-07-21T04:45:55Z","markets":[{"key":"totals","last_update":"2025-07-21T04:45:55Z","outcomes":[{"name":"Over","price":1.91,"point":33},{"name":"Under","price":1.91,"point":33}]}]},{"key":"grosvenor","title":"Grosvenor","last_update":"2025-07-21T04:46:31Z","markets":[{"key":"totals","last_update":"2025-07-21T04:46:31Z","outcomes":[{"name":"Over","price":1.92,"point":32.5},{"name":"Under","price":1.89,"point":32.5}]}]},{"key":"betrivers","title":"BetRivers","last_update":"2025-07-21T04:46:31Z","markets":[{"key":"h2h","last_update":"2025-07-21T04:46:31Z","outcomes":[{"name":"Detroit Lions","price":1.89},{"name":"Los Angeles Chargers","price":1.89}]},{"key":"totals","last_update":"2025-07-21T04:46:31Z","outcomes":[{"name":"Over","price":1.91,"point":32.5},{"name":"Under","price":1.88,"point":32.5}]}]},{"key":"unibet","title":"Unibet","last_update":"2025-07-21T04:45:55Z","markets":[{"key":"totals","last_update":"2025-07-21T04:45:55Z","outcomes":[{"name":"Over","price":1.92,"point":32.5},{"name":"Under","price":1.89,"point":32.5}]}]},{"key":"tabtouch","title":"TABtouch","last_update":"2025-07-21T04:45:55Z","markets":[{"key":"totals","last_update":"2025-07-21T04:45:55Z","outcomes":[{"name":"Over","price":1.92,"point":32.5},{"name":"Under","price":1.89,"point":32.5}]}]}]}]}