{"timestamp":1753101966125,"data":[{"id":"aec9362c0a4372ecd2fdda660bb8d3ad","sport_key":"aussierules_afl","sport_title":"AFL","commence_time":"2025-07-24T09:30:28Z","home_team":"Hawthorn Hawks","away_team":"Carlton Blues","bookmakers":[{"key":"sportsbet","title":"SportsBet","last_update":"2025-07-21T04:46:13Z","markets":[{"key":"h2h","last_update":"2025-07-21T04:46:13Z","outcomes":[{"name":"Carlton Blues","price":5.1},{"name":"Hawthorn Hawks","price":1.17}]}]},{"key":"paddypower","title":"Paddy Power","last_update":"2025-07-21T04:45:30Z","markets":[{"key":"h2h","last_update":"2025-07-21T04:45:30Z","outcomes":[{"name":"Carlton Blues","price":4.5},{"name":"Hawthorn Hawks","price":1.2}]}]},{"key":"marathonbet","title":"Marathon Bet","last_update":"2025-07-21T04:45:31Z","markets":[{"key":"h2h","last_update":"2025-07-21T04:45:31Z","outcomes":[{"name":"Carlton Blues","price":5.3},{"name":"Hawthorn Hawks","price":1.15}]}]},{"key":"tab","title":"TAB","last_update":"2025-07-21T04:45:32Z","markets":[{"key":"h2h","last_update":"2025-07-21T04:45:32Z","outcomes":[{"name":"Carlton Blues","price":5},{"name":"Hawthorn Hawks","price":1.17}]},{"key":"totals","last_update":"2025-07-21T04:45:32Z","outcomes":[{"name":"Over","price":1.9,"point":160.5},{"name":"Under","price":1.9,"point":160.5}]}]},{"key":"betfair_ex_au","title":"Betfair","last_update":"2025-07-21T04:45:49Z","markets":[{"key":"h2h","last_update":"2025-07-21T04:45:49Z","outcomes":[{"name":"Carlton Blues","price":6.4},{"name":"Hawthorn Hawks","price":1.17}]},{"key":"h2h_lay","last_update":"2025-07-21T04:45:49Z","outcomes":[{"name":"Carlton Blues","price":7},{"name":"Hawthorn Hawks","price":1.18}]}]},{"key":"betfair_ex_eu","title":"Betfair","last_update":"2025-07-21T04:46:02Z","markets":[{"key":"h2h","last_update":"2025-07-21T04:46:02Z","outcomes":[{"name":"Carlton Blues","price":6.4},{"name":"Hawthorn Hawks","price":1.17}]},{"key":"h2h_lay","last_update":"2025-07-21T04:46:02Z","outcomes":[{"name":"Carlton Blues","price":7},{"name":"Hawthorn Hawks","price":1.18}]}]},{"key":"betfair_ex_uk","title":"Betfair","last_update":"2025-07-21T04:45:31Z","markets":[{"key":"h2h","last_update":"2025-07-21T04:45:31Z","outcomes":[{"name":"Carlton Blues","price":6.4},{"name":"Hawthorn Hawks","price":1.17}]},{"key":"h2h_lay","last_update":"2025-07-21T04:45:31Z","outcomes":[{"name":"Carlton Blues","price":7},{"name":"Hawthorn Hawks","price":1.18}]}]},{"key":"bovada","title":"Bovada","last_update":"2025-07-21T04:45:30Z","markets":[{"key":"h2h","last_update":"2025-07-21T04:45:30Z","outcomes":[{"name":"Carlton Blues","price":5.25},{"name":"Hawthorn Hawks","price":1.14}]}]},{"key":"betright","title":"Bet Right","last_update":"2025-07-21T04:46:13Z","markets":[{"key":"h2h","last_update":"2025-07-21T04:46:13Z","outcomes":[{"name":"Carlton Blues","price":5},{"name":"Hawthorn Hawks","price":1.17}]}]},{"key":"coolbet","title":"Coolbet","last_update":"2025-07-21T04:45:31Z","markets":[{"key":"h2h","last_update":"2025-07-21T04:45:31Z","outcomes":[{"name":"Carlton Blues","price":5.1},{"name":"Hawthorn Hawks","price":1.17}]},{"key":"totals","last_update":"2025-07-21T04:45:31Z","outcomes":[{"name":"Over","price":1.85,"point":160.5},{"name":"Under","price":1.85,"point":160.5}]}]},{"key":"betr_au","title":"Betr","last_update":"2025-07-21T04:46:13Z","markets":[{"key":"h2h","last_update":"2025-07-21T04:46:13Z","outcomes":[{"name":"Carlton Blues","price":4.85},{"name":"Hawthorn Hawks","price":1.18}]}]},{"key":"boombet","title":"BoomBet","last_update":"2025-07-21T04:46:24Z","markets":[{"key":"h2h","last_update":"2025-07-21T04:46:24Z","outcomes":[{"name":"Carlton Blues","price":5},{"name":"Hawthorn Hawks","price":1.17}]}]},{"key":"betsson","title":"Betsson","last_update":"2025-07-21T04:46:12Z","markets":[{"key":"h2h","last_update":"2025-07-21T04:46:12Z","outcomes":[{"name":"Carlton Blues","price":4.48},{"name":"Hawthorn Hawks","price":1.16}]}]},{"key":"nordicbet","title":"Nordic Bet","last_update":"2025-07-21T04:45:47Z","markets":[{"key":"h2h","last_update":"2025-07-21T04:45:47Z","outcomes":[{"name":"Carlton Blues","price":4.48},{"name":"Hawthorn Hawks","price":1.16}]}]},{"key":"draftkings","title":"DraftKings","last_update":"2025-07-21T04:46:01Z","markets":[{"key":"h2h","last_update":"2025-07-21T04:46:01Z","outcomes":[{"name":"Carlton Blues","price":4.3},{"name":"Hawthorn Hawks","price":1.2}]}]},{"key":"neds","title":"Neds","last_update":"2025-07-21T04:46:13Z","markets":[{"key":"h2h","last_update":"2025-07-21T04:46:13Z","outcomes":[{"name":"Carlton Blues","price":4.8},{"name":"Hawthorn Hawks","price":1.18}]}]},{"key":"ladbrokes_au","title":"Ladbrokes","last_update":"2025-07-21T04:46:12Z","markets":[{"key":"h2h","last_update":"2025-07-21T04:46:12Z","outcomes":[{"name":"Carlton Blues","price":4.8},{"name":"Hawthorn Hawks","price":1.18}]}]},{"key":"playup","title":"PlayUp","last_update":"2025-07-21T04:46:14Z","markets":[{"key":"h2h","last_update":"2025-07-21T04:46:14Z","outcomes":[{"name":"Carlton Blues","price":5.1},{"name":"Hawthorn Hawks","price":1.17}]}]},{"key":"pointsbetau","title":"PointsBet (AU)","last_update":"2025-07-21T04:46:13Z","markets":[{"key":"h2h","last_update":"2025-07-21T04:46:13Z","outcomes":[{"name":"Carlton Blues","price":5},{"name":"Hawthorn Hawks","price":1.17}]}]},{"key":"everygame","title":"Everygame","last_update":"2025-07-21T04:45:31Z","markets":[{"key":"h2h","last_update":"2025-07-21T04:45:31Z","outcomes":[{"name":"Carlton Blues","price":4.5},{"name":"Hawthorn Hawks","price":1.16}]}]},{"key":"tabtouch","title":"TABtouch","last_update":"2025-07-21T04:46:13Z","markets":[{"key":"h2h","last_update":"2025-07-21T04:46:13Z","outcomes":[{"name":"Carlton Blues","price":4.9},{"name":"Hawthorn Hawks","price":1.18}]}]},{"key":"grosvenor","title":"Grosvenor","last_update":"2025-07-21T04:45:30Z","markets":[{"key":"h2h","last_update":"2025-07-21T04:45:30Z","outcomes":[{"name":"Carlton Blues","price":4.9},{"name":"Hawthorn Hawks","price":1.18}]}]},{"key":"unibet_nl","title":"Unibet (NL)","last_update":"2025-07-21T04:45:30Z","markets":[{"key":"h2h","last_update":"2025-07-21T04:45:30Z","outcomes":[{"name":"Carlton Blues","price":4.9},{"name":"Hawthorn Hawks","price":1.18}]}]},{"key":"unibet","title":"Unibet","last_update":"2025-07-21T04:45:31Z","markets":[{"key":"h2h","last_update":"2025-07-21T04:45:31Z","outcomes":[{"name":"Carlton Blues","price":4.75},{"name":"Hawthorn Hawks","price":1.17}]}]},{"key":"casumo","title":"Casumo","last_update":"2025-07-21T04:45:30Z","markets":[{"key":"h2h","last_update":"2025-07-21T04:45:30Z","outcomes":[{"name":"Carlton Blues","price":4.9},{"name":"Hawthorn Hawks","price":1.18}]}]},{"key":"tipico_de","title":"Tipico","last_update":"2025-07-21T04:46:13Z","markets":[{"key":"h2h","last_update":"2025-07-21T04:46:13Z","outcomes":[{"name":"Carlton Blues","price":4.3},{"name":"Hawthorn Hawks","price":1.18}]}]}]},{"id":"03b338db37c86eec44eeb173ae65bd0e","sport_key":"aussierules_afl","sport_title":"AFL","commence_time":"2025-07-25T09:20:09Z","home_team":"Essendon Bombers","away_team":"Western Bulldogs","bookmakers":[{"key":"sportsbet","title":"SportsBet","last_update":"2025-07-21T04:46:13Z","markets":[{"key":"h2h","last_update":"2025-07-21T04:46:13Z","outcomes":[{"name":"Essendon Bombers","price":11},{"name":"Western Bulldogs","price":1.04}]}]},{"key":"paddypower","title":"Paddy Power","last_update":"2025-07-21T04:45:30Z","markets":[{"key":"h2h","last_update":"2025-07-21T04:45:30Z","outcomes":[{"name":"Essendon Bombers","price":9},{"name":"Western Bulldogs","price":1.05}]}]},{"key":"marathonbet","title":"Marathon Bet","last_update":"2025-07-21T04:45:31Z","markets":[{"key":"h2h","last_update":"2025-07-21T04:45:31Z","outcomes":[{"name":"Essendon Bombers","price":15.5},{"name":"Western Bulldogs","price":1.01}]}]},{"key":"tab","title":"TAB","last_update":"2025-07-21T04:45:32Z","markets":[{"key":"h2h","last_update":"2025-07-21T04:45:32Z","outcomes":[{"name":"Essendon Bombers","price":11},{"name":"Western Bulldogs","price":1.04}]}]},{"key":"betfair_ex_au","title":"Betfair","last_update":"2025-07-21T04:45:49Z","markets":[{"key":"h2h","last_update":"2025-07-21T04:45:49Z","outcomes":[{"name":"Essendon Bombers","price":15.5},{"name":"Western Bulldogs","price":1.05}]},{"key":"h2h_lay","last_update":"2025-07-21T04:45:49Z","outcomes":[{"name":"Essendon Bombers","price":19},{"name":"Western Bulldogs","price":1.06}]}]},{"key":"betfair_ex_uk","title":"Betfair","last_update":"2025-07-21T04:45:31Z","markets":[{"key":"h2h","last_update":"2025-07-21T04:45:31Z","outcomes":[{"name":"Essendon Bombers","price":15.5},{"name":"Western Bulldogs","price":1.05}]},{"key":"h2h_lay","last_update":"2025-07-21T04:45:31Z","outcomes":[{"name":"Essendon Bombers","price":19},{"name":"Western Bulldogs","price":1.06}]}]},{"key":"betfair_ex_eu","title":"Betfair","last_update":"2025-07-21T04:46:02Z","markets":[{"key":"h2h","last_update":"2025-07-21T04:46:02Z","outcomes":[{"name":"Essendon Bombers","price":15.5},{"name":"Western Bulldogs","price":1.05}]},{"key":"h2h_lay","last_update":"2025-07-21T04:46:02Z","outcomes":[{"name":"Essendon Bombers","price":19},{"name":"Western Bulldogs","price":1.06}]}]},{"key":"betright","title":"Bet Right","last_update":"2025-07-21T04:46:13Z","markets":[{"key":"h2h","last_update":"2025-07-21T04:46:13Z","outcomes":[{"name":"Essendon Bombers","price":11},{"name":"Western Bulldogs","price":1.04}]}]},{"key":"coolbet","title":"Coolbet","last_update":"2025-07-21T04:45:31Z","markets":[{"key":"h2h","last_update":"2025-07-21T04:45:31Z","outcomes":[{"name":"Essendon Bombers","price":11.5},{"name":"Western Bulldogs","price":1.04}]}]},{"key":"nordicbet","title":"Nordic Bet","last_update":"2025-07-21T04:45:47Z","markets":[{"key":"h2h","last_update":"2025-07-21T04:45:47Z","outcomes":[{"name":"Essendon Bombers","price":8},{"name":"Western Bulldogs","price":1.03}]}]},{"key":"betsson","title":"Betsson","last_update":"2025-07-21T04:46:12Z","markets":[{"key":"h2h","last_update":"2025-07-21T04:46:12Z","outcomes":[{"name":"Essendon Bombers","price":8},{"name":"Western Bulldogs","price":1.03}]}]},{"key":"betr_au","title":"Betr","last_update":"2025-07-21T04:46:13Z","markets":[{"key":"h2h","last_update":"2025-07-21T04:46:13Z","outcomes":[{"name":"Essendon Bombers","price":12},{"name":"Western Bulldogs","price":1.03}]}]},{"key":"draftkings","title":"DraftKings","last_update":"2025-07-21T04:46:01Z","markets":[{"key":"h2h","last_update":"2025-07-21T04:46:01Z","outcomes":[{"name":"Essendon Bombers","price":9},{"name":"Western Bulldogs","price":1.05}]}]},{"key":"boombet","title":"BoomBet","last_update":"2025-07-21T04:46:24Z","markets":[{"key":"h2h","last_update":"2025-07-21T04:46:24Z","outcomes":[{"name":"Essendon Bombers","price":11},{"name":"Western Bulldogs","price":1.04}]}]},{"key":"ladbrokes_au","title":"Ladbrokes","last_update":"2025-07-21T04:46:12Z","markets":[{"key":"h2h","last_update":"2025-07-21T04:46:12Z","outcomes":[{"name":"Essendon Bombers","price":11},{"name":"Western Bulldogs","price":1.04}]}]},{"key":"neds","title":"Neds","last_update":"2025-07-21T04:46:13Z","markets":[{"key":"h2h","last_update":"2025-07-21T04:46:13Z","outcomes":[{"name":"Essendon Bombers","price":11},{"name":"Western Bulldogs","price":1.04}]}]},{"key":"playup","title":"PlayUp","last_update":"2025-07-21T04:46:14Z","markets":[{"key":"h2h","last_update":"2025-07-21T04:46:14Z","outcomes":[{"name":"Essendon Bombers","price":11},{"name":"Western Bulldogs","price":1.04}]}]},{"key":"pointsbetau","title":"PointsBet (AU)","last_update":"2025-07-21T04:46:13Z","markets":[{"key":"h2h","last_update":"2025-07-21T04:46:13Z","outcomes":[{"name":"Essendon Bombers","price":11},{"name":"Western Bulldogs","price":1.04}]}]},{"key":"everygame","title":"Everygame","last_update":"2025-07-21T04:45:31Z","markets":[{"key":"h2h","last_update":"2025-07-21T04:45:31Z","outcomes":[{"name":"Essendon Bombers","price":9},{"name":"Western Bulldogs","price":1.03}]}]},{"key":"tabtouch","title":"TABtouch","last_update":"2025-07-21T04:46:13Z","markets":[{"key":"h2h","last_update":"2025-07-21T04:46:13Z","outcomes":[{"name":"Essendon Bombers","price":12},{"name":"Western Bulldogs","price":1.03}]}]},{"key":"casumo","title":"Casumo","last_update":"2025-07-21T04:45:30Z","markets":[{"key":"h2h","last_update":"2025-07-21T04:45:30Z","outcomes":[{"name":"Essendon Bombers","price":12},{"name":"Western Bulldogs","price":1.03}]}]},{"key":"unibet_nl","title":"Unibet (NL)","last_update":"2025-07-21T04:45:30Z","markets":[{"key":"h2h","last_update":"2025-07-21T04:45:30Z","outcomes":[{"name":"Essendon Bombers","price":12},{"name":"Western Bulldogs","price":1.03}]}]},{"key":"grosvenor","title":"Grosvenor","last_update":"2025-07-21T04:45:30Z","markets":[{"key":"h2h","last_update":"2025-07-21T04:45:30Z","outcomes":[{"name":"Essendon Bombers","price":12},{"name":"Western Bulldogs","price":1.03}]}]},{"key":"unibet","title":"Unibet","last_update":"2025-07-21T04:45:31Z","markets":[{"key":"h2h","last_update":"2025-07-21T04:45:31Z","outcomes":[{"name":"Essendon Bombers","price":12},{"name":"Western Bulldogs","price":1.02}]}]},{"key":"tipico_de","title":"Tipico","last_update":"2025-07-21T04:46:13Z","markets":[{"key":"h2h","last_update":"2025-07-21T04:46:13Z","outcomes":[{"name":"Essendon Bombers","price":9},{"name":"Western Bulldogs","price":1.03}]}]}]},{"id":"744d89a8134ff2035952c4a7036a701a","sport_key":"aussierules_afl","sport_title":"AFL","commence_time":"2025-07-25T09:50:02Z","home_team":"Greater Western Sydney Giants","away_team":"Sydney Swans","bookmakers":[{"key":"sportsbet","title":"SportsBet","last_update":"2025-07-21T04:46:13Z","markets":[{"key":"h2h","last_update":"2025-07-21T04:46:13Z","outcomes":[{"name":"Greater Western Sydney Giants","price":1.58},{"name":"Sydney Swans","price":2.4}]}]},{"key":"paddypower","title":"Paddy Power","last_update":"2025-07-21T04:45:30Z","markets":[{"key":"h2h","last_update":"2025-07-21T04:45:30Z","outcomes":[{"name":"Greater Western Sydney Giants","price":1.62},{"name":"Sydney Swans","price":2.25}]}]},{"key":"marathonbet","title":"Marathon Bet","last_update":"2025-07-21T04:45:31Z","markets":[{"key":"h2h","last_update":"2025-07-21T04:45:31Z","outcomes":[{"name":"Greater Western Sydney Giants","price":1.61},{"name":"Sydney Swans","price":2.29}]}]},{"key":"tab","title":"TAB","last_update":"2025-07-21T04:45:32Z","markets":[{"key":"h2h","last_update":"2025-07-21T04:45:32Z","outcomes":[{"name":"Greater Western Sydney Giants","price":1.58},{"name":"Sydney Swans","price":2.4}]}]},{"key":"betfair_ex_uk","title":"Betfair","last_update":"2025-07-21T04:45:31Z","markets":[{"key":"h2h","last_update":"2025-07-21T04:45:31Z","outcomes":[{"name":"Greater Western Sydney Giants","price":1.56},{"name":"Sydney Swans","price":2.56}]},{"key":"h2h_lay","last_update":"2025-07-21T04:45:31Z","outcomes":[{"name":"Greater Western Sydney Giants","price":1.64},{"name":"Sydney Swans","price":2.78}]}]},{"key":"betfair_ex_au","title":"Betfair","last_update":"2025-07-21T04:45:49Z","markets":[{"key":"h2h","last_update":"2025-07-21T04:45:49Z","outcomes":[{"name":"Greater Western Sydney Giants","price":1.56},{"name":"Sydney Swans","price":2.56}]},{"key":"h2h_lay","last_update":"2025-07-21T04:45:49Z","outcomes":[{"name":"Greater Western Sydney Giants","price":1.65},{"name":"Sydney Swans","price":2.78}]}]},{"key":"betfair_ex_eu","title":"Betfair","last_update":"2025-07-21T04:46:02Z","markets":[{"key":"h2h","last_update":"2025-07-21T04:46:02Z","outcomes":[{"name":"Greater Western Sydney Giants","price":1.56},{"name":"Sydney Swans","price":2.56}]},{"key":"h2h_lay","last_update":"2025-07-21T04:46:02Z","outcomes":[{"name":"Greater Western Sydney Giants","price":1.64},{"name":"Sydney Swans","price":2.78}]}]},{"key":"bovada","title":"Bovada","last_update":"2025-07-21T04:45:30Z","markets":[{"key":"h2h","last_update":"2025-07-21T04:45:30Z","outcomes":[{"name":"Greater Western Sydney Giants","price":1.59},{"name":"Sydney Swans","price":2.3}]}]},{"key":"betright","title":"Bet Right","last_update":"2025-07-21T04:46:13Z","markets":[{"key":"h2h","last_update":"2025-07-21T04:46:13Z","outcomes":[{"name":"Greater Western Sydney Giants","price":1.58},{"name":"Sydney Swans","price":2.38}]}]},{"key":"coolbet","title":"Coolbet","last_update":"2025-07-21T04:45:31Z","markets":[{"key":"h2h","last_update":"2025-07-21T04:45:31Z","outcomes":[{"name":"Greater Western Sydney Giants","price":1.58},{"name":"Sydney Swans","price":2.4}]}]},{"key":"betsson","title":"Betsson","last_update":"2025-07-21T04:46:12Z","markets":[{"key":"h2h","last_update":"2025-07-21T04:46:12Z","outcomes":[{"name":"Greater Western Sydney Giants","price":1.54},{"name":"Sydney Swans","price":2.29}]}]},{"key":"nordicbet","title":"Nordic Bet","last_update":"2025-07-21T04:45:47Z","markets":[{"key":"h2h","last_update":"2025-07-21T04:45:47Z","outcomes":[{"name":"Greater Western Sydney Giants","price":1.54},{"name":"Sydney Swans","price":2.29}]}]},{"key":"draftkings","title":"DraftKings","last_update":"2025-07-21T04:46:01Z","markets":[{"key":"h2h","last_update":"2025-07-21T04:46:01Z","outcomes":[{"name":"Greater Western Sydney Giants","price":1.62},{"name":"Sydney Swans","price":2.2}]}]},{"key":"boombet","title":"BoomBet","last_update":"2025-07-21T04:46:24Z","markets":[{"key":"h2h","last_update":"2025-07-21T04:46:24Z","outcomes":[{"name":"Greater Western Sydney Giants","price":1.57},{"name":"Sydney Swans","price":2.38}]}]},{"key":"neds","title":"Neds","last_update":"2025-07-21T04:46:13Z","markets":[{"key":"h2h","last_update":"2025-07-21T04:46:13Z","outcomes":[{"name":"Greater Western Sydney Giants","price":1.57},{"name":"Sydney Swans","price":2.4}]}]},{"key":"ladbrokes_au","title":"Ladbrokes","last_update":"2025-07-21T04:46:12Z","markets":[{"key":"h2h","last_update":"2025-07-21T04:46:12Z","outcomes":[{"name":"Greater Western Sydney Giants","price":1.57},{"name":"Sydney Swans","price":2.4}]}]},{"key":"betr_au","title":"Betr","last_update":"2025-07-21T04:46:13Z","markets":[{"key":"h2h","last_update":"2025-07-21T04:46:13Z","outcomes":[{"name":"Greater Western Sydney Giants","price":1.55},{"name":"Sydney Swans","price":2.45}]}]},{"key":"playup","title":"PlayUp","last_update":"2025-07-21T04:46:14Z","markets":[{"key":"h2h","last_update":"2025-07-21T04:46:14Z","outcomes":[{"name":"Greater Western Sydney Giants","price":1.55},{"name":"Sydney Swans","price":2.45}]}]},{"key":"pointsbetau","title":"PointsBet (AU)","last_update":"2025-07-21T04:46:13Z","markets":[{"key":"h2h","last_update":"2025-07-21T04:46:13Z","outcomes":[{"name":"Greater Western Sydney Giants","price":1.56},{"name":"Sydney Swans","price":2.5}]}]},{"key":"everygame","title":"Everygame","last_update":"2025-07-21T04:45:31Z","markets":[{"key":"h2h","last_update":"2025-07-21T04:45:31Z","outcomes":[{"name":"Greater Western Sydney Giants","price":1.55},{"name":"Sydney Swans","price":2.3}]}]},{"key":"tabtouch","title":"TABtouch","last_update":"2025-07-21T04:46:13Z","markets":[{"key":"h2h","last_update":"2025-07-21T04:46:13Z","outcomes":[{"name":"Greater Western Sydney Giants","price":1.61},{"name":"Sydney Swans","price":2.32}]}]},{"key":"casumo","title":"Casumo","last_update":"2025-07-21T04:45:30Z","markets":[{"key":"h2h","last_update":"2025-07-21T04:45:30Z","outcomes":[{"name":"Greater Western Sydney Giants","price":1.61},{"name":"Sydney Swans","price":2.32}]}]},{"key":"grosvenor","title":"Grosvenor","last_update":"2025-07-21T04:45:30Z","markets":[{"key":"h2h","last_update":"2025-07-21T04:45:30Z","outcomes":[{"name":"Greater Western Sydney Giants","price":1.61},{"name":"Sydney Swans","price":2.32}]}]},{"key":"unibet_nl","title":"Unibet (NL)","last_update":"2025-07-21T04:45:30Z","markets":[{"key":"h2h","last_update":"2025-07-21T04:45:30Z","outcomes":[{"name":"Greater Western Sydney Giants","price":1.61},{"name":"Sydney Swans","price":2.32}]}]},{"key":"unibet","title":"Unibet","last_update":"2025-07-21T04:45:31Z","markets":[{"key":"h2h","last_update":"2025-07-21T04:45:31Z","outcomes":[{"name":"Greater Western Sydney Giants","price":1.58},{"name":"Sydney Swans","price":2.32}]}]},{"key":"tipico_de","title":"Tipico","last_update":"2025-07-21T04:46:13Z","markets":[{"key":"h2h","last_update":"2025-07-21T04:46:13Z","outcomes":[{"name":"Greater Western Sydney Giants","price":1.6},{"name":"Sydney Swans","price":2.2}]}]}]},{"id":"ff8aba093a23f318e1a0bc178e39ae1e","sport_key":"aussierules_afl","sport_title":"AFL","commence_time":"2025-07-26T03:20:22Z","home_team":"Gold Coast Suns","away_team":"Brisbane Lions","bookmakers":[{"key":"sportsbet","title":"SportsBet","last_update":"2025-07-21T04:46:13Z","markets":[{"key":"h2h","last_update":"2025-07-21T04:46:13Z","outcomes":[{"name":"Brisbane Lions","price":1.59},{"name":"Gold Coast Suns","price":2.37}]}]},{"key":"paddypower","title":"Paddy Power","last_update":"2025-07-21T04:45:30Z","markets":[{"key":"h2h","last_update":"2025-07-21T04:45:30Z","outcomes":[{"name":"Brisbane Lions","price":1.62},{"name":"Gold Coast Suns","price":2.25}]}]},{"key":"marathonbet","title":"Marathon Bet","last_update":"2025-07-21T04:45:31Z","markets":[{"key":"h2h","last_update":"2025-07-21T04:45:31Z","outcomes":[{"name":"Brisbane Lions","price":1.65},{"name":"Gold Coast Suns","price":2.21}]}]},{"key":"tab","title":"TAB","last_update":"2025-07-21T04:45:32Z","markets":[{"key":"h2h","last_update":"2025-07-21T04:45:32Z","outcomes":[{"name":"Brisbane Lions","price":1.62},{"name":"Gold Coast Suns","price":2.3}]}]},{"key":"betfair_ex_au","title":"Betfair","last_update":"2025-07-21T04:45:49Z","markets":[{"key":"h2h","last_update":"2025-07-21T04:45:49Z","outcomes":[{"name":"Brisbane Lions","price":1.62},{"name":"Gold Coast Suns","price":2.4}]},{"key":"h2h_lay","last_update":"2025-07-21T04:45:49Z","outcomes":[{"name":"Brisbane Lions","price":1.72},{"name":"Gold Coast Suns","price":2.62}]}]},{"key":"betfair_ex_uk","title":"Betfair","last_update":"2025-07-21T04:45:31Z","markets":[{"key":"h2h","last_update":"2025-07-21T04:45:31Z","outcomes":[{"name":"Brisbane Lions","price":1.62},{"name":"Gold Coast Suns","price":2.4}]},{"key":"h2h_lay","last_update":"2025-07-21T04:45:31Z","outcomes":[{"name":"Brisbane Lions","price":1.72},{"name":"Gold Coast Suns","price":2.62}]}]},{"key":"betfair_ex_eu","title":"Betfair","last_update":"2025-07-21T04:46:02Z","markets":[{"key":"h2h","last_update":"2025-07-21T04:46:02Z","outcomes":[{"name":"Brisbane Lions","price":1.62},{"name":"Gold Coast Suns","price":2.4}]},{"key":"h2h_lay","last_update":"2025-07-21T04:46:02Z","outcomes":[{"name":"Brisbane Lions","price":1.72},{"name":"Gold Coast Suns","price":2.62}]}]},{"key":"bovada","title":"Bovada","last_update":"2025-07-21T04:45:30Z","markets":[{"key":"h2h","last_update":"2025-07-21T04:45:30Z","outcomes":[{"name":"Brisbane Lions","price":1.65},{"name":"Gold Coast Suns","price":2.2}]}]},{"key":"betright","title":"Bet Right","last_update":"2025-07-21T04:46:13Z","markets":[{"key":"h2h","last_update":"2025-07-21T04:46:13Z","outcomes":[{"name":"Brisbane Lions","price":1.62},{"name":"Gold Coast Suns","price":2.3}]}]},{"key":"coolbet","title":"Coolbet","last_update":"2025-07-21T04:45:31Z","markets":[{"key":"h2h","last_update":"2025-07-21T04:45:31Z","outcomes":[{"name":"Brisbane Lions","price":1.62},{"name":"Gold Coast Suns","price":2.3}]}]},{"key":"betsson","title":"Betsson","last_update":"2025-07-21T04:46:12Z","markets":[{"key":"h2h","last_update":"2025-07-21T04:46:12Z","outcomes":[{"name":"Brisbane Lions","price":1.59},{"name":"Gold Coast Suns","price":2.19}]}]},{"key":"nordicbet","title":"Nordic Bet","last_update":"2025-07-21T04:45:47Z","markets":[{"key":"h2h","last_update":"2025-07-21T04:45:47Z","outcomes":[{"name":"Brisbane Lions","price":1.59},{"name":"Gold Coast Suns","price":2.19}]}]},{"key":"draftkings","title":"DraftKings","last_update":"2025-07-21T04:46:01Z","markets":[{"key":"h2h","last_update":"2025-07-21T04:46:01Z","outcomes":[{"name":"Brisbane Lions","price":1.62},{"name":"Gold Coast Suns","price":2.2}]}]},{"key":"neds","title":"Neds","last_update":"2025-07-21T04:46:13Z","markets":[{"key":"h2h","last_update":"2025-07-21T04:46:13Z","outcomes":[{"name":"Brisbane Lions","price":1.64},{"name":"Gold Coast Suns","price":2.25}]}]},{"key":"ladbrokes_au","title":"Ladbrokes","last_update":"2025-07-21T04:46:12Z","markets":[{"key":"h2h","last_update":"2025-07-21T04:46:12Z","outcomes":[{"name":"Brisbane Lions","price":1.64},{"name":"Gold Coast Suns","price":2.25}]}]},{"key":"pointsbetau","title":"PointsBet (AU)","last_update":"2025-07-21T04:46:13Z","markets":[{"key":"h2h","last_update":"2025-07-21T04:46:13Z","outcomes":[{"name":"Brisbane Lions","price":1.6},{"name":"Gold Coast Suns","price":2.35}]}]},{"key":"everygame","title":"Everygame","last_update":"2025-07-21T04:45:31Z","markets":[{"key":"h2h","last_update":"2025-07-21T04:45:31Z","outcomes":[{"name":"Brisbane Lions","price":1.6},{"name":"Gold Coast Suns","price":2.2}]}]},{"key":"boombet","title":"BoomBet","last_update":"2025-07-21T04:46:24Z","markets":[{"key":"h2h","last_update":"2025-07-21T04:46:24Z","outcomes":[{"name":"Brisbane Lions","price":1.62},{"name":"Gold Coast Suns","price":2.3}]}]},{"key":"playup","title":"PlayUp","last_update":"2025-07-21T04:46:14Z","markets":[{"key":"h2h","last_update":"2025-07-21T04:46:14Z","outcomes":[{"name":"Brisbane Lions","price":1.65},{"name":"Gold Coast Suns","price":2.25}]}]},{"key":"betr_au","title":"Betr","last_update":"2025-07-21T04:46:13Z","markets":[{"key":"h2h","last_update":"2025-07-21T04:46:13Z","outcomes":[{"name":"Brisbane Lions","price":1.65},{"name":"Gold Coast Suns","price":2.25}]}]},{"key":"tipico_de","title":"Tipico","last_update":"2025-07-21T04:46:13Z","markets":[{"key":"h2h","last_update":"2025-07-21T04:46:13Z","outcomes":[{"name":"Brisbane Lions","price":1.6},{"name":"Gold Coast Suns","price":2.2}]}]},{"key":"casumo","title":"Casumo","last_update":"2025-07-21T04:45:30Z","markets":[{"key":"h2h","last_update":"2025-07-21T04:45:30Z","outcomes":[{"name":"Brisbane Lions","price":1.62},{"name":"Gold Coast Suns","price":2.28}]}]},{"key":"grosvenor","title":"Grosvenor","last_update":"2025-07-21T04:45:30Z","markets":[{"key":"h2h","last_update":"2025-07-21T04:45:30Z","outcomes":[{"name":"Brisbane Lions","price":1.62},{"name":"Gold Coast Suns","price":2.28}]}]},{"key":"unibet_nl","title":"Unibet (NL)","last_update":"2025-07-21T04:45:30Z","markets":[{"key":"h2h","last_update":"2025-07-21T04:45:30Z","outcomes":[{"name":"Brisbane Lions","price":1.62},{"name":"Gold Coast Suns","price":2.28}]}]},{"key":"unibet","title":"Unibet","last_update":"2025-07-21T04:45:31Z","markets":[{"key":"h2h","last_update":"2025-07-21T04:45:31Z","outcomes":[{"name":"Brisbane Lions","price":1.61},{"name":"Gold Coast Suns","price":2.25}]}]},{"key":"tabtouch","title":"TABtouch","last_update":"2025-07-21T04:46:13Z","markets":[{"key":"h2h","last_update":"2025-07-21T04:46:13Z","outcomes":[{"name":"Brisbane Lions","price":1.62},{"name":"Gold Coast Suns","price":2.28}]}]}]},{"id":"e78cd3430cec311e15c0da949258e9f6","sport_key":"aussierules_afl","sport_title":"AFL","commence_time":"2025-07-26T06:15:37Z","home_team":"Fremantle Dockers","away_team":"West Coast Eagles","bookmakers":[{"key":"sportsbet","title":"SportsBet","last_update":"2025-07-21T04:46:13Z","markets":[{"key":"h2h","last_update":"2025-07-21T04:46:13Z","outcomes":[{"name":"Fremantle Dockers","price":1.04},{"name":"West Coast Eagles","price":12.5}]}]},{"key":"paddypower","title":"Paddy Power","last_update":"2025-07-21T04:45:30Z","markets":[{"key":"h2h","last_update":"2025-07-21T04:45:30Z","outcomes":[{"name":"Fremantle Dockers","price":1.05},{"name":"West Coast Eagles","price":10}]}]},{"key":"marathonbet","title":"Marathon Bet","last_update":"2025-07-21T04:45:31Z","markets":[{"key":"h2h","last_update":"2025-07-21T04:45:31Z","outcomes":[{"name":"Fremantle Dockers","price":1.05},{"name":"West Coast Eagles","price":9.6}]}]},{"key":"tab","title":"TAB","last_update":"2025-07-21T04:45:32Z","markets":[{"key":"h2h","last_update":"2025-07-21T04:45:32Z","outcomes":[{"name":"Fremantle Dockers","price":1.04},{"name":"West Coast Eagles","price":11}]}]},{"key":"betfair_ex_uk","title":"Betfair","last_update":"2025-07-21T04:45:31Z","markets":[{"key":"h2h","last_update":"2025-07-21T04:45:31Z","outcomes":[{"name":"Fremantle Dockers","price":1.06},{"name":"West Coast Eagles","price":15.5}]},{"key":"h2h_lay","last_update":"2025-07-21T04:45:31Z","outcomes":[{"name":"Fremantle Dockers","price":1.07},{"name":"West Coast Eagles","price":18}]}]},{"key":"betfair_ex_au","title":"Betfair","last_update":"2025-07-21T04:45:49Z","markets":[{"key":"h2h","last_update":"2025-07-21T04:45:49Z","outcomes":[{"name":"Fremantle Dockers","price":1.06},{"name":"West Coast Eagles","price":15.5}]},{"key":"h2h_lay","last_update":"2025-07-21T04:45:49Z","outcomes":[{"name":"Fremantle Dockers","price":1.07},{"name":"West Coast Eagles","price":18}]}]},{"key":"betfair_ex_eu","title":"Betfair","last_update":"2025-07-21T04:46:02Z","markets":[{"key":"h2h","last_update":"2025-07-21T04:46:02Z","outcomes":[{"name":"Fremantle Dockers","price":1.06},{"name":"West Coast Eagles","price":15.5}]},{"key":"h2h_lay","last_update":"2025-07-21T04:46:02Z","outcomes":[{"name":"Fremantle Dockers","price":1.07},{"name":"West Coast Eagles","price":18}]}]},{"key":"bovada","title":"Bovada","last_update":"2025-07-21T04:45:30Z","markets":[{"key":"h2h","last_update":"2025-07-21T04:45:30Z","outcomes":[{"name":"Fremantle Dockers","price":1.06},{"name":"West Coast Eagles","price":9}]}]},{"key":"betright","title":"Bet Right","last_update":"2025-07-21T04:46:13Z","markets":[{"key":"h2h","last_update":"2025-07-21T04:46:13Z","outcomes":[{"name":"Fremantle Dockers","price":1.04},{"name":"West Coast Eagles","price":11}]}]},{"key":"coolbet","title":"Coolbet","last_update":"2025-07-21T04:45:31Z","markets":[{"key":"h2h","last_update":"2025-07-21T04:45:31Z","outcomes":[{"name":"Fremantle Dockers","price":1.05},{"name":"West Coast Eagles","price":10.5}]}]},{"key":"nordicbet","title":"Nordic Bet","last_update":"2025-07-21T04:45:47Z","markets":[{"key":"h2h","last_update":"2025-07-21T04:45:47Z","outcomes":[{"name":"Fremantle Dockers","price":1.03},{"name":"West Coast Eagles","price":8}]}]},{"key":"betsson","title":"Betsson","last_update":"2025-07-21T04:46:12Z","markets":[{"key":"h2h","last_update":"2025-07-21T04:46:12Z","outcomes":[{"name":"Fremantle Dockers","price":1.03},{"name":"West Coast Eagles","price":8}]}]},{"key":"ladbrokes_au","title":"Ladbrokes","last_update":"2025-07-21T04:46:12Z","markets":[{"key":"h2h","last_update":"2025-07-21T04:46:12Z","outcomes":[{"name":"Fremantle Dockers","price":1.04},{"name":"West Coast Eagles","price":11}]}]},{"key":"neds","title":"Neds","last_update":"2025-07-21T04:46:13Z","markets":[{"key":"h2h","last_update":"2025-07-21T04:46:13Z","outcomes":[{"name":"Fremantle Dockers","price":1.04},{"name":"West Coast Eagles","price":11}]}]},{"key":"playup","title":"PlayUp","last_update":"2025-07-21T04:46:14Z","markets":[{"key":"h2h","last_update":"2025-07-21T04:46:14Z","outcomes":[{"name":"Fremantle Dockers","price":1.04},{"name":"West Coast Eagles","price":11}]}]},{"key":"everygame","title":"Everygame","last_update":"2025-07-21T04:45:31Z","markets":[{"key":"h2h","last_update":"2025-07-21T04:45:31Z","outcomes":[{"name":"Fremantle Dockers","price":1.03},{"name":"West Coast Eagles","price":9}]}]},{"key":"betr_au","title":"Betr","last_update":"2025-07-21T04:46:13Z","markets":[{"key":"h2h","last_update":"2025-07-21T04:46:13Z","outcomes":[{"name":"Fremantle Dockers","price":1.05},{"name":"West Coast Eagles","price":10}]}]},{"key":"boombet","title":"BoomBet","last_update":"2025-07-21T04:46:24Z","markets":[{"key":"h2h","last_update":"2025-07-21T04:46:24Z","outcomes":[{"name":"Fremantle Dockers","price":1.03},{"name":"West Coast Eagles","price":11.5}]}]},{"key":"pointsbetau","title":"PointsBet (AU)","last_update":"2025-07-21T04:46:13Z","markets":[{"key":"h2h","last_update":"2025-07-21T04:46:13Z","outcomes":[{"name":"Fremantle Dockers","price":1.05},{"name":"West Coast Eagles","price":10}]}]},{"key":"draftkings","title":"DraftKings","last_update":"2025-07-21T04:46:01Z","markets":[{"key":"h2h","last_update":"2025-07-21T04:46:01Z","outcomes":[{"name":"Fremantle Dockers","price":1.04},{"name":"West Coast Eagles","price":9.5}]}]},{"key":"tipico_de","title":"Tipico","last_update":"2025-07-21T04:46:13Z","markets":[{"key":"h2h","last_update":"2025-07-21T04:46:13Z","outcomes":[{"name":"Fremantle Dockers","price":1.03},{"name":"West Coast Eagles","price":9}]}]},{"key":"tabtouch","title":"TABtouch","last_update":"2025-07-21T04:46:13Z","markets":[{"key":"h2h","last_update":"2025-07-21T04:46:13Z","outcomes":[{"name":"Fremantle Dockers","price":1.04},{"name":"West Coast Eagles","price":11}]}]},{"key":"casumo","title":"Casumo","last_update":"2025-07-21T04:45:30Z","markets":[{"key":"h2h","last_update":"2025-07-21T04:45:30Z","outcomes":[{"name":"Fremantle Dockers","price":1.04},{"name":"West Coast Eagles","price":11}]}]},{"key":"grosvenor","title":"Grosvenor","last_update":"2025-07-21T04:45:30Z","markets":[{"key":"h2h","last_update":"2025-07-21T04:45:30Z","outcomes":[{"name":"Fremantle Dockers","price":1.04},{"name":"West Coast Eagles","price":11}]}]},{"key":"unibet_nl","title":"Unibet (NL)","last_update":"2025-07-21T04:45:30Z","markets":[{"key":"h2h","last_update":"2025-07-21T04:45:30Z","outcomes":[{"name":"Fremantle Dockers","price":1.04},{"name":"West Coast Eagles","price":11}]}]},{"key":"unibet","title":"Unibet","last_update":"2025-07-21T04:45:31Z","markets":[{"key":"h2h","last_update":"2025-07-21T04:45:31Z","outcomes":[{"name":"Fremantle Dockers","price":1.03},{"name":"West Coast Eagles","price":10.5}]}]}]},{"id":"4f31bb8153868503e3a057c25a505a08","sport_key":"aussierules_afl","sport_title":"AFL","commence_time":"2025-07-26T09:35:23Z","home_team":"North Melbourne Kangaroos","away_team":"Geelong Cats","bookmakers":[{"key":"sportsbet","title":"SportsBet","last_update":"2025-07-21T04:46:13Z","markets":[{"key":"h2h","last_update":"2025-07-21T04:46:13Z","outcomes":[{"name":"Geelong Cats","price":1.1},{"name":"North Melbourne Kangaroos","price":7}]}]},{"key":"paddypower","title":"Paddy Power","last_update":"2025-07-21T04:45:30Z","markets":[{"key":"h2h","last_update":"2025-07-21T04:45:30Z","outcomes":[{"name":"Geelong Cats","price":1.11},{"name":"North Melbourne Kangaroos","price":6.5}]}]},{"key":"marathonbet","title":"Marathon Bet","last_update":"2025-07-21T04:45:31Z","markets":[{"key":"h2h","last_update":"2025-07-21T04:45:31Z","outcomes":[{"name":"Geelong Cats","price":1.09},{"name":"North Melbourne Kangaroos","price":7.2}]}]},{"key":"tab","title":"TAB","last_update":"2025-07-21T04:45:32Z","markets":[{"key":"h2h","last_update":"2025-07-21T04:45:32Z","outcomes":[{"name":"Geelong Cats","price":1.09},{"name":"North Melbourne Kangaroos","price":7.5}]}]},{"key":"betfair_ex_uk","title":"Betfair","last_update":"2025-07-21T04:45:31Z","markets":[{"key":"h2h","last_update":"2025-07-21T04:45:31Z","outcomes":[{"name":"Geelong Cats","price":1.12},{"name":"North Melbourne Kangaroos","price":8.8}]},{"key":"h2h_lay","last_update":"2025-07-21T04:45:31Z","outcomes":[{"name":"Geelong Cats","price":1.13},{"name":"North Melbourne Kangaroos","price":10.5}]}]},{"key":"betfair_ex_eu","title":"Betfair","last_update":"2025-07-21T04:46:02Z","markets":[{"key":"h2h","last_update":"2025-07-21T04:46:02Z","outcomes":[{"name":"Geelong Cats","price":1.12},{"name":"North Melbourne Kangaroos","price":8.8}]},{"key":"h2h_lay","last_update":"2025-07-21T04:46:02Z","outcomes":[{"name":"Geelong Cats","price":1.13},{"name":"North Melbourne Kangaroos","price":10.5}]}]},{"key":"betfair_ex_au","title":"Betfair","last_update":"2025-07-21T04:45:49Z","markets":[{"key":"h2h","last_update":"2025-07-21T04:45:49Z","outcomes":[{"name":"Geelong Cats","price":1.12},{"name":"North Melbourne Kangaroos","price":8.8}]},{"key":"h2h_lay","last_update":"2025-07-21T04:45:49Z","outcomes":[{"name":"Geelong Cats","price":1.13},{"name":"North Melbourne Kangaroos","price":11}]}]},{"key":"bovada","title":"Bovada","last_update":"2025-07-21T04:45:30Z","markets":[{"key":"h2h","last_update":"2025-07-21T04:45:30Z","outcomes":[{"name":"Geelong Cats","price":1.09},{"name":"North Melbourne Kangaroos","price":7}]}]},{"key":"betright","title":"Bet Right","last_update":"2025-07-21T04:46:13Z","markets":[{"key":"h2h","last_update":"2025-07-21T04:46:13Z","outcomes":[{"name":"Geelong Cats","price":1.09},{"name":"North Melbourne Kangaroos","price":7.5}]}]},{"key":"coolbet","title":"Coolbet","last_update":"2025-07-21T04:45:31Z","markets":[{"key":"h2h","last_update":"2025-07-21T04:45:31Z","outcomes":[{"name":"Geelong Cats","price":1.1},{"name":"North Melbourne Kangaroos","price":7.1}]}]},{"key":"betsson","title":"Betsson","last_update":"2025-07-21T04:46:12Z","markets":[{"key":"h2h","last_update":"2025-07-21T04:46:12Z","outcomes":[{"name":"Geelong Cats","price":1.08},{"name":"North Melbourne Kangaroos","price":6.2}]}]},{"key":"nordicbet","title":"Nordic Bet","last_update":"2025-07-21T04:45:47Z","markets":[{"key":"h2h","last_update":"2025-07-21T04:45:47Z","outcomes":[{"name":"Geelong Cats","price":1.08},{"name":"North Melbourne Kangaroos","price":6.2}]}]},{"key":"draftkings","title":"DraftKings","last_update":"2025-07-21T04:46:01Z","markets":[{"key":"h2h","last_update":"2025-07-21T04:46:01Z","outcomes":[{"name":"Geelong Cats","price":1.1},{"name":"North Melbourne Kangaroos","price":6}]}]},{"key":"neds","title":"Neds","last_update":"2025-07-21T04:46:13Z","markets":[{"key":"h2h","last_update":"2025-07-21T04:46:13Z","outcomes":[{"name":"Geelong Cats","price":1.09},{"name":"North Melbourne Kangaroos","price":7.5}]}]},{"key":"ladbrokes_au","title":"Ladbrokes","last_update":"2025-07-21T04:46:12Z","markets":[{"key":"h2h","last_update":"2025-07-21T04:46:12Z","outcomes":[{"name":"Geelong Cats","price":1.09},{"name":"North Melbourne Kangaroos","price":7.5}]}]},{"key":"everygame","title":"Everygame","last_update":"2025-07-21T04:45:31Z","markets":[{"key":"h2h","last_update":"2025-07-21T04:45:31Z","outcomes":[{"name":"Geelong Cats","price":1.07},{"name":"North Melbourne Kangaroos","price":7}]}]},{"key":"boombet","title":"BoomBet","last_update":"2025-07-21T04:46:24Z","markets":[{"key":"h2h","last_update":"2025-07-21T04:46:24Z","outcomes":[{"name":"Geelong Cats","price":1.09},{"name":"North Melbourne Kangaroos","price":7.2}]}]},{"key":"playup","title":"PlayUp","last_update":"2025-07-21T04:46:14Z","markets":[{"key":"h2h","last_update":"2025-07-21T04:46:14Z","outcomes":[{"name":"Geelong Cats","price":1.09},{"name":"North Melbourne Kangaroos","price":7.5}]}]},{"key":"betr_au","title":"Betr","last_update":"2025-07-21T04:46:13Z","markets":[{"key":"h2h","last_update":"2025-07-21T04:46:13Z","outcomes":[{"name":"Geelong Cats","price":1.09},{"name":"North Melbourne Kangaroos","price":7.5}]}]},{"key":"pointsbetau","title":"PointsBet (AU)","last_update":"2025-07-21T04:46:13Z","markets":[{"key":"h2h","last_update":"2025-07-21T04:46:13Z","outcomes":[{"name":"Geelong Cats","price":1.08},{"name":"North Melbourne Kangaroos","price":8}]}]},{"key":"tipico_de","title":"Tipico","last_update":"2025-07-21T04:46:13Z","markets":[{"key":"h2h","last_update":"2025-07-21T04:46:13Z","outcomes":[{"name":"Geelong Cats","price":1.07},{"name":"North Melbourne Kangaroos","price":7}]}]},{"key":"casumo","title":"Casumo","last_update":"2025-07-21T04:45:30Z","markets":[{"key":"h2h","last_update":"2025-07-21T04:45:30Z","outcomes":[{"name":"Geelong Cats","price":1.09},{"name":"North Melbourne Kangaroos","price":7.5}]}]},{"key":"grosvenor","title":"Grosvenor","last_update":"2025-07-21T04:45:30Z","markets":[{"key":"h2h","last_update":"2025-07-21T04:45:30Z","outcomes":[{"name":"Geelong Cats","price":1.09},{"name":"North Melbourne Kangaroos","price":7.5}]}]},{"key":"unibet_nl","title":"Unibet (NL)","last_update":"2025-07-21T04:45:30Z","markets":[{"key":"h2h","last_update":"2025-07-21T04:45:30Z","outcomes":[{"name":"Geelong Cats","price":1.09},{"name":"North Melbourne Kangaroos","price":7.5}]}]},{"key":"tabtouch","title":"TABtouch","last_update":"2025-07-21T04:46:13Z","markets":[{"key":"h2h","last_update":"2025-07-21T04:46:13Z","outcomes":[{"name":"Geelong Cats","price":1.09},{"name":"North Melbourne Kangaroos","price":7.5}]}]},{"key":"unibet","title":"Unibet","last_update":"2025-07-21T04:45:31Z","markets":[{"key":"h2h","last_update":"2025-07-21T04:45:31Z","outcomes":[{"name":"Geelong Cats","price":1.07},{"name":"North Melbourne Kangaroos","price":7.5}]}]}]},{"id":"547f7215d0ea8ee6b41f07e645d5cccb","sport_key":"aussierules_afl","sport_title":"AFL","commence_time":"2025-07-26T10:10:02Z","home_team":"Adelaide Crows","away_team":"Port Adelaide Power","bookmakers":[{"key":"sportsbet","title":"SportsBet","last_update":"2025-07-21T04:46:13Z","markets":[{"key":"h2h","last_update":"2025-07-21T04:46:13Z","outcomes":[{"name":"Adelaide Crows","price":1.17},{"name":"Port Adelaide Power","price":5.1}]}]},{"key":"paddypower","title":"Paddy Power","last_update":"2025-07-21T04:45:30Z","markets":[{"key":"h2h","last_update":"2025-07-21T04:45:30Z","outcomes":[{"name":"Adelaide Crows","price":1.2},{"name":"Port Adelaide Power","price":4.5}]}]},{"key":"marathonbet","title":"Marathon Bet","last_update":"2025-07-21T04:45:31Z","markets":[{"key":"h2h","last_update":"2025-07-21T04:45:31Z","outcomes":[{"name":"Adelaide Crows","price":1.19},{"name":"Port Adelaide Power","price":4.6}]}]},{"key":"tab","title":"TAB","last_update":"2025-07-21T04:45:32Z","markets":[{"key":"h2h","last_update":"2025-07-21T04:45:32Z","outcomes":[{"name":"Adelaide Crows","price":1.17},{"name":"Port Adelaide Power","price":5}]}]},{"key":"betfair_ex_uk","title":"Betfair","last_update":"2025-07-21T04:45:31Z","markets":[{"key":"h2h","last_update":"2025-07-21T04:45:31Z","outcomes":[{"name":"Adelaide Crows","price":1.18},{"name":"Port Adelaide Power","price":6}]},{"key":"h2h_lay","last_update":"2025-07-21T04:45:31Z","outcomes":[{"name":"Adelaide Crows","price":1.2},{"name":"Port Adelaide Power","price":6.8}]}]},{"key":"betfair_ex_eu","title":"Betfair","last_update":"2025-07-21T04:46:02Z","markets":[{"key":"h2h","last_update":"2025-07-21T04:46:02Z","outcomes":[{"name":"Adelaide Crows","price":1.18},{"name":"Port Adelaide Power","price":6}]},{"key":"h2h_lay","last_update":"2025-07-21T04:46:02Z","outcomes":[{"name":"Adelaide Crows","price":1.2},{"name":"Port Adelaide Power","price":6.8}]}]},{"key":"betfair_ex_au","title":"Betfair","last_update":"2025-07-21T04:45:49Z","markets":[{"key":"h2h","last_update":"2025-07-21T04:45:49Z","outcomes":[{"name":"Adelaide Crows","price":1.18},{"name":"Port Adelaide Power","price":6}]},{"key":"h2h_lay","last_update":"2025-07-21T04:45:49Z","outcomes":[{"name":"Adelaide Crows","price":1.2},{"name":"Port Adelaide Power","price":6.8}]}]},{"key":"betright","title":"Bet Right","last_update":"2025-07-21T04:46:13Z","markets":[{"key":"h2h","last_update":"2025-07-21T04:46:13Z","outcomes":[{"name":"Adelaide Crows","price":1.17},{"name":"Port Adelaide Power","price":5}]}]},{"key":"coolbet","title":"Coolbet","last_update":"2025-07-21T04:45:31Z","markets":[{"key":"h2h","last_update":"2025-07-21T04:45:31Z","outcomes":[{"name":"Adelaide Crows","price":1.18},{"name":"Port Adelaide Power","price":4.9}]}]},{"key":"draftkings","title":"DraftKings","last_update":"2025-07-21T04:46:01Z","markets":[{"key":"h2h","last_update":"2025-07-21T04:46:01Z","outcomes":[{"name":"Adelaide Crows","price":1.2},{"name":"Port Adelaide Power","price":4.3}]}]},{"key":"betsson","title":"Betsson","last_update":"2025-07-21T04:46:12Z","markets":[{"key":"h2h","last_update":"2025-07-21T04:46:12Z","outcomes":[{"name":"Adelaide Crows","price":1.16},{"name":"Port Adelaide Power","price":4.41}]}]},{"key":"nordicbet","title":"Nordic Bet","last_update":"2025-07-21T04:45:47Z","markets":[{"key":"h2h","last_update":"2025-07-21T04:45:47Z","outcomes":[{"name":"Adelaide Crows","price":1.16},{"name":"Port Adelaide Power","price":4.41}]}]},{"key":"neds","title":"Neds","last_update":"2025-07-21T04:46:13Z","markets":[{"key":"h2h","last_update":"2025-07-21T04:46:13Z","outcomes":[{"name":"Adelaide Crows","price":1.18},{"name":"Port Adelaide Power","price":4.8}]}]},{"key":"ladbrokes_au","title":"Ladbrokes","last_update":"2025-07-21T04:46:12Z","markets":[{"key":"h2h","last_update":"2025-07-21T04:46:12Z","outcomes":[{"name":"Adelaide Crows","price":1.18},{"name":"Port Adelaide Power","price":4.8}]}]},{"key":"everygame","title":"Everygame","last_update":"2025-07-21T04:45:31Z","markets":[{"key":"h2h","last_update":"2025-07-21T04:45:31Z","outcomes":[{"name":"Adelaide Crows","price":1.16},{"name":"Port Adelaide Power","price":4.5}]}]},{"key":"boombet","title":"BoomBet","last_update":"2025-07-21T04:46:24Z","markets":[{"key":"h2h","last_update":"2025-07-21T04:46:24Z","outcomes":[{"name":"Adelaide Crows","price":1.17},{"name":"Port Adelaide Power","price":5}]}]},{"key":"pointsbetau","title":"PointsBet (AU)","last_update":"2025-07-21T04:46:13Z","markets":[{"key":"h2h","last_update":"2025-07-21T04:46:13Z","outcomes":[{"name":"Adelaide Crows","price":1.18},{"name":"Port Adelaide Power","price":4.75}]}]},{"key":"playup","title":"PlayUp","last_update":"2025-07-21T04:46:14Z","markets":[{"key":"h2h","last_update":"2025-07-21T04:46:14Z","outcomes":[{"name":"Adelaide Crows","price":1.17},{"name":"Port Adelaide Power","price":5.1}]}]},{"key":"betr_au","title":"Betr","last_update":"2025-07-21T04:46:13Z","markets":[{"key":"h2h","last_update":"2025-07-21T04:46:13Z","outcomes":[{"name":"Adelaide Crows","price":1.18},{"name":"Port Adelaide Power","price":4.85}]}]},{"key":"tipico_de","title":"Tipico","last_update":"2025-07-21T04:46:13Z","markets":[{"key":"h2h","last_update":"2025-07-21T04:46:13Z","outcomes":[{"name":"Adelaide Crows","price":1.15},{"name":"Port Adelaide Power","price":4.7}]}]},{"key":"tabtouch","title":"TABtouch","last_update":"2025-07-21T04:46:13Z","markets":[{"key":"h2h","last_update":"2025-07-21T04:46:13Z","outcomes":[{"name":"Adelaide Crows","price":1.18},{"name":"Port Adelaide Power","price":4.9}]}]},{"key":"casumo","title":"Casumo","last_update":"2025-07-21T04:45:30Z","markets":[{"key":"h2h","last_update":"2025-07-21T04:45:30Z","outcomes":[{"name":"Adelaide Crows","price":1.18},{"name":"Port Adelaide Power","price":4.9}]}]},{"key":"grosvenor","title":"Grosvenor","last_update":"2025-07-21T04:45:30Z","markets":[{"key":"h2h","last_update":"2025-07-21T04:45:30Z","outcomes":[{"name":"Adelaide Crows","price":1.18},{"name":"Port Adelaide Power","price":4.9}]}]},{"key":"unibet_nl","title":"Unibet (NL)","last_update":"2025-07-21T04:45:30Z","markets":[{"key":"h2h","last_update":"2025-07-21T04:45:30Z","outcomes":[{"name":"Adelaide Crows","price":1.18},{"name":"Port Adelaide Power","price":4.9}]}]},{"key":"unibet","title":"Unibet","last_update":"2025-07-21T04:45:31Z","markets":[{"key":"h2h","last_update":"2025-07-21T04:45:31Z","outcomes":[{"name":"Adelaide Crows","price":1.16},{"name":"Port Adelaide Power","price":4.9}]}]}]},{"id":"6e9d5ee8f3be4ef5364f81bbd2267d13","sport_key":"aussierules_afl","sport_title":"AFL","commence_time":"2025-07-27T04:10:34Z","home_team":"Richmond Tigers","away_team":"Collingwood Magpies","bookmakers":[{"key":"sportsbet","title":"SportsBet","last_update":"2025-07-21T04:46:13Z","markets":[{"key":"h2h","last_update":"2025-07-21T04:46:13Z","outcomes":[{"name":"Collingwood Magpies","price":1.05},{"name":"Richmond Tigers","price":10.5}]}]},{"key":"paddypower","title":"Paddy Power","last_update":"2025-07-21T04:45:30Z","markets":[{"key":"h2h","last_update":"2025-07-21T04:45:30Z","outcomes":[{"name":"Collingwood Magpies","price":1.06},{"name":"Richmond Tigers","price":9}]}]},{"key":"marathonbet","title":"Marathon Bet","last_update":"2025-07-21T04:45:31Z","markets":[{"key":"h2h","last_update":"2025-07-21T04:45:31Z","outcomes":[{"name":"Collingwood Magpies","price":1.06},{"name":"Richmond Tigers","price":8.5}]}]},{"key":"tab","title":"TAB","last_update":"2025-07-21T04:45:32Z","markets":[{"key":"h2h","last_update":"2025-07-21T04:45:32Z","outcomes":[{"name":"Collingwood Magpies","price":1.05},{"name":"Richmond Tigers","price":10}]}]},{"key":"betfair_ex_au","title":"Betfair","last_update":"2025-07-21T04:45:49Z","markets":[{"key":"h2h","last_update":"2025-07-21T04:45:49Z","outcomes":[{"name":"Collingwood Magpies","price":1.07},{"name":"Richmond Tigers","price":13.5}]},{"key":"h2h_lay","last_update":"2025-07-21T04:45:49Z","outcomes":[{"name":"Collingwood Magpies","price":1.08},{"name":"Richmond Tigers","price":15.5}]}]},{"key":"betfair_ex_eu","title":"Betfair","last_update":"2025-07-21T04:46:02Z","markets":[{"key":"h2h","last_update":"2025-07-21T04:46:02Z","outcomes":[{"name":"Collingwood Magpies","price":1.07},{"name":"Richmond Tigers","price":13.5}]},{"key":"h2h_lay","last_update":"2025-07-21T04:46:02Z","outcomes":[{"name":"Collingwood Magpies","price":1.08},{"name":"Richmond Tigers","price":15.5}]}]},{"key":"betfair_ex_uk","title":"Betfair","last_update":"2025-07-21T04:45:31Z","markets":[{"key":"h2h","last_update":"2025-07-21T04:45:31Z","outcomes":[{"name":"Collingwood Magpies","price":1.07},{"name":"Richmond Tigers","price":13.5}]},{"key":"h2h_lay","last_update":"2025-07-21T04:45:31Z","outcomes":[{"name":"Collingwood Magpies","price":1.08},{"name":"Richmond Tigers","price":15.5}]}]},{"key":"betright","title":"Bet Right","last_update":"2025-07-21T04:46:13Z","markets":[{"key":"h2h","last_update":"2025-07-21T04:46:13Z","outcomes":[{"name":"Collingwood Magpies","price":1.06},{"name":"Richmond Tigers","price":9.5}]}]},{"key":"bovada","title":"Bovada","last_update":"2025-07-21T04:45:30Z","markets":[{"key":"h2h","last_update":"2025-07-21T04:45:30Z","outcomes":[{"name":"Collingwood Magpies","price":1.06},{"name":"Richmond Tigers","price":8.5}]}]},{"key":"draftkings","title":"DraftKings","last_update":"2025-07-21T04:46:01Z","markets":[{"key":"h2h","last_update":"2025-07-21T04:46:01Z","outcomes":[{"name":"Collingwood Magpies","price":1.06},{"name":"Richmond Tigers","price":8.5}]}]},{"key":"ladbrokes_au","title":"Ladbrokes","last_update":"2025-07-21T04:46:12Z","markets":[{"key":"h2h","last_update":"2025-07-21T04:46:12Z","outcomes":[{"name":"Collingwood Magpies","price":1.06},{"name":"Richmond Tigers","price":9.25}]}]},{"key":"neds","title":"Neds","last_update":"2025-07-21T04:46:13Z","markets":[{"key":"h2h","last_update":"2025-07-21T04:46:13Z","outcomes":[{"name":"Collingwood Magpies","price":1.06},{"name":"Richmond Tigers","price":9.25}]}]},{"key":"coolbet","title":"Coolbet","last_update":"2025-07-21T04:45:31Z","markets":[{"key":"h2h","last_update":"2025-07-21T04:45:31Z","outcomes":[{"name":"Collingwood Magpies","price":1.06},{"name":"Richmond Tigers","price":9.5}]}]},{"key":"everygame","title":"Everygame","last_update":"2025-07-21T04:45:31Z","markets":[{"key":"h2h","last_update":"2025-07-21T04:45:31Z","outcomes":[{"name":"Collingwood Magpies","price":1.04},{"name":"Richmond Tigers","price":8.5}]}]},{"key":"nordicbet","title":"Nordic Bet","last_update":"2025-07-21T04:45:47Z","markets":[{"key":"h2h","last_update":"2025-07-21T04:45:47Z","outcomes":[{"name":"Collingwood Magpies","price":1.04},{"name":"Richmond Tigers","price":7.4}]}]},{"key":"betsson","title":"Betsson","last_update":"2025-07-21T04:46:12Z","markets":[{"key":"h2h","last_update":"2025-07-21T04:46:12Z","outcomes":[{"name":"Collingwood Magpies","price":1.04},{"name":"Richmond Tigers","price":7.4}]}]},{"key":"betr_au","title":"Betr","last_update":"2025-07-21T04:46:13Z","markets":[{"key":"h2h","last_update":"2025-07-21T04:46:13Z","outcomes":[{"name":"Collingwood Magpies","price":1.06},{"name":"Richmond Tigers","price":9}]}]},{"key":"boombet","title":"BoomBet","last_update":"2025-07-21T04:46:24Z","markets":[{"key":"h2h","last_update":"2025-07-21T04:46:24Z","outcomes":[{"name":"Collingwood Magpies","price":1.05},{"name":"Richmond Tigers","price":10}]}]},{"key":"pointsbetau","title":"PointsBet (AU)","last_update":"2025-07-21T04:46:13Z","markets":[{"key":"h2h","last_update":"2025-07-21T04:46:13Z","outcomes":[{"name":"Collingwood Magpies","price":1.06},{"name":"Richmond Tigers","price":9}]}]},{"key":"playup","title":"PlayUp","last_update":"2025-07-21T04:46:14Z","markets":[{"key":"h2h","last_update":"2025-07-21T04:46:14Z","outcomes":[{"name":"Collingwood Magpies","price":1.05},{"name":"Richmond Tigers","price":10}]}]},{"key":"tipico_de","title":"Tipico","last_update":"2025-07-21T04:46:13Z","markets":[{"key":"h2h","last_update":"2025-07-21T04:46:13Z","outcomes":[{"name":"Collingwood Magpies","price":1.05},{"name":"Richmond Tigers","price":8}]}]},{"key":"tabtouch","title":"TABtouch","last_update":"2025-07-21T04:46:13Z","markets":[{"key":"h2h","last_update":"2025-07-21T04:46:13Z","outcomes":[{"name":"Collingwood Magpies","price":1.06},{"name":"Richmond Tigers","price":9.5}]}]},{"key":"unibet_nl","title":"Unibet (NL)","last_update":"2025-07-21T04:45:30Z","markets":[{"key":"h2h","last_update":"2025-07-21T04:45:30Z","outcomes":[{"name":"Collingwood Magpies","price":1.06},{"name":"Richmond Tigers","price":9.5}]}]},{"key":"casumo","title":"Casumo","last_update":"2025-07-21T04:45:30Z","markets":[{"key":"h2h","last_update":"2025-07-21T04:45:30Z","outcomes":[{"name":"Collingwood Magpies","price":1.06},{"name":"Richmond Tigers","price":9.5}]}]},{"key":"grosvenor","title":"Grosvenor","last_update":"2025-07-21T04:45:30Z","markets":[{"key":"h2h","last_update":"2025-07-21T04:45:30Z","outcomes":[{"name":"Collingwood Magpies","price":1.06},{"name":"Richmond Tigers","price":9.5}]}]},{"key":"unibet","title":"Unibet","last_update":"2025-07-21T04:45:31Z","markets":[{"key":"h2h","last_update":"2025-07-21T04:45:31Z","outcomes":[{"name":"Collingwood Magpies","price":1.05},{"name":"Richmond Tigers","price":9}]}]}]},{"id":"6d14387ec82e2a8db3b7e61c98a623ae","sport_key":"aussierules_afl","sport_title":"AFL","commence_time":"2025-07-27T05:15:44Z","home_team":"St Kilda Saints","away_team":"Melbourne Demons","bookmakers":[{"key":"sportsbet","title":"SportsBet","last_update":"2025-07-21T04:46:13Z","markets":[{"key":"h2h","last_update":"2025-07-21T04:46:13Z","outcomes":[{"name":"Melbourne Demons","price":1.74},{"name":"St Kilda Saints","price":2.1}]}]},{"key":"paddypower","title":"Paddy Power","last_update":"2025-07-21T04:45:30Z","markets":[{"key":"h2h","last_update":"2025-07-21T04:45:30Z","outcomes":[{"name":"Melbourne Demons","price":1.73},{"name":"St Kilda Saints","price":2.1}]}]},{"key":"marathonbet","title":"Marathon Bet","last_update":"2025-07-21T04:45:31Z","markets":[{"key":"h2h","last_update":"2025-07-21T04:45:31Z","outcomes":[{"name":"Melbourne Demons","price":1.76},{"name":"St Kilda Saints","price":2.04}]}]},{"key":"tab","title":"TAB","last_update":"2025-07-21T04:45:32Z","markets":[{"key":"h2h","last_update":"2025-07-21T04:45:32Z","outcomes":[{"name":"Melbourne Demons","price":1.74},{"name":"St Kilda Saints","price":2.1}]}]},{"key":"betfair_ex_eu","title":"Betfair","last_update":"2025-07-21T04:46:02Z","markets":[{"key":"h2h","last_update":"2025-07-21T04:46:02Z","outcomes":[{"name":"Melbourne Demons","price":1.84},{"name":"St Kilda Saints","price":2.1}]},{"key":"h2h_lay","last_update":"2025-07-21T04:46:02Z","outcomes":[{"name":"Melbourne Demons","price":1.91},{"name":"St Kilda Saints","price":2.18}]}]},{"key":"betfair_ex_uk","title":"Betfair","last_update":"2025-07-21T04:45:31Z","markets":[{"key":"h2h","last_update":"2025-07-21T04:45:31Z","outcomes":[{"name":"Melbourne Demons","price":1.84},{"name":"St Kilda Saints","price":2.1}]},{"key":"h2h_lay","last_update":"2025-07-21T04:45:31Z","outcomes":[{"name":"Melbourne Demons","price":1.91},{"name":"St Kilda Saints","price":2.18}]}]},{"key":"betfair_ex_au","title":"Betfair","last_update":"2025-07-21T04:45:49Z","markets":[{"key":"h2h","last_update":"2025-07-21T04:45:49Z","outcomes":[{"name":"Melbourne Demons","price":1.84},{"name":"St Kilda Saints","price":2.1}]},{"key":"h2h_lay","last_update":"2025-07-21T04:45:49Z","outcomes":[{"name":"Melbourne Demons","price":1.91},{"name":"St Kilda Saints","price":2.18}]}]},{"key":"bovada","title":"Bovada","last_update":"2025-07-21T04:45:30Z","markets":[{"key":"h2h","last_update":"2025-07-21T04:45:30Z","outcomes":[{"name":"Melbourne Demons","price":1.74},{"name":"St Kilda Saints","price":2.05}]}]},{"key":"betright","title":"Bet Right","last_update":"2025-07-21T04:46:13Z","markets":[{"key":"h2h","last_update":"2025-07-21T04:46:13Z","outcomes":[{"name":"Melbourne Demons","price":1.74},{"name":"St Kilda Saints","price":2.1}]}]},{"key":"draftkings","title":"DraftKings","last_update":"2025-07-21T04:46:01Z","markets":[{"key":"h2h","last_update":"2025-07-21T04:46:01Z","outcomes":[{"name":"Melbourne Demons","price":1.65},{"name":"St Kilda Saints","price":2.15}]}]},{"key":"neds","title":"Neds","last_update":"2025-07-21T04:46:13Z","markets":[{"key":"h2h","last_update":"2025-07-21T04:46:13Z","outcomes":[{"name":"Melbourne Demons","price":1.7},{"name":"St Kilda Saints","price":2.15}]}]},{"key":"ladbrokes_au","title":"Ladbrokes","last_update":"2025-07-21T04:46:12Z","markets":[{"key":"h2h","last_update":"2025-07-21T04:46:12Z","outcomes":[{"name":"Melbourne Demons","price":1.7},{"name":"St Kilda Saints","price":2.15}]}]},{"key":"playup","title":"PlayUp","last_update":"2025-07-21T04:46:14Z","markets":[{"key":"h2h","last_update":"2025-07-21T04:46:14Z","outcomes":[{"name":"Melbourne Demons","price":1.74},{"name":"St Kilda Saints","price":2.1}]}]},{"key":"coolbet","title":"Coolbet","last_update":"2025-07-21T04:45:31Z","markets":[{"key":"h2h","last_update":"2025-07-21T04:45:31Z","outcomes":[{"name":"Melbourne Demons","price":1.75},{"name":"St Kilda Saints","price":2.1}]}]},{"key":"betsson","title":"Betsson","last_update":"2025-07-21T04:46:12Z","markets":[{"key":"h2h","last_update":"2025-07-21T04:46:12Z","outcomes":[{"name":"Melbourne Demons","price":1.71},{"name":"St Kilda Saints","price":1.99}]}]},{"key":"boombet","title":"BoomBet","last_update":"2025-07-21T04:46:24Z","markets":[{"key":"h2h","last_update":"2025-07-21T04:46:24Z","outcomes":[{"name":"Melbourne Demons","price":1.74},{"name":"St Kilda Saints","price":2.1}]}]},{"key":"nordicbet","title":"Nordic Bet","last_update":"2025-07-21T04:45:47Z","markets":[{"key":"h2h","last_update":"2025-07-21T04:45:47Z","outcomes":[{"name":"Melbourne Demons","price":1.71},{"name":"St Kilda Saints","price":1.99}]}]},{"key":"betr_au","title":"Betr","last_update":"2025-07-21T04:46:13Z","markets":[{"key":"h2h","last_update":"2025-07-21T04:46:13Z","outcomes":[{"name":"Melbourne Demons","price":1.77},{"name":"St Kilda Saints","price":2.05}]}]},{"key":"pointsbetau","title":"PointsBet (AU)","last_update":"2025-07-21T04:46:13Z","markets":[{"key":"h2h","last_update":"2025-07-21T04:46:13Z","outcomes":[{"name":"Melbourne Demons","price":1.77},{"name":"St Kilda Saints","price":2.05}]}]},{"key":"tipico_de","title":"Tipico","last_update":"2025-07-21T04:46:13Z","markets":[{"key":"h2h","last_update":"2025-07-21T04:46:13Z","outcomes":[{"name":"Melbourne Demons","price":1.75},{"name":"St Kilda Saints","price":1.95}]}]},{"key":"unibet_nl","title":"Unibet (NL)","last_update":"2025-07-21T04:45:30Z","markets":[{"key":"h2h","last_update":"2025-07-21T04:45:30Z","outcomes":[{"name":"Melbourne Demons","price":1.77},{"name":"St Kilda Saints","price":2.05}]}]},{"key":"casumo","title":"Casumo","last_update":"2025-07-21T04:45:30Z","markets":[{"key":"h2h","last_update":"2025-07-21T04:45:30Z","outcomes":[{"name":"Melbourne Demons","price":1.77},{"name":"St Kilda Saints","price":2.05}]}]},{"key":"grosvenor","title":"Grosvenor","last_update":"2025-07-21T04:45:30Z","markets":[{"key":"h2h","last_update":"2025-07-21T04:45:30Z","outcomes":[{"name":"Melbourne Demons","price":1.77},{"name":"St Kilda Saints","price":2.05}]}]},{"key":"unibet","title":"Unibet","last_update":"2025-07-21T04:45:31Z","markets":[{"key":"h2h","last_update":"2025-07-21T04:45:31Z","outcomes":[{"name":"Melbourne Demons","price":1.74},{"name":"St Kilda Saints","price":2.05}]}]},{"key":"tabtouch","title":"TABtouch","last_update":"2025-07-21T04:46:13Z","markets":[{"key":"h2h","last_update":"2025-07-21T04:46:13Z","outcomes":[{"name":"Melbourne Demons","price":1.77},{"name":"St Kilda Saints","price":2.05}]}]}]},{"id":"ecd1c5b2ecf2a07544b9aa98d54eab32","sport_key":"aussierules_afl","sport_title":"AFL","commence_time":"2025-07-31T09:30:06Z","home_team":"Western Bulldogs","away_team":"Greater Western Sydney Giants","bookmakers":[{"key":"sportsbet","title":"SportsBet","last_update":"2025-07-21T04:46:13Z","markets":[{"key":"h2h","last_update":"2025-07-21T04:46:13Z","outcomes":[{"name":"Greater Western Sydney Giants","price":2.26},{"name":"Western Bulldogs","price":1.64}]}]},{"key":"paddypower","title":"Paddy Power","last_update":"2025-07-21T04:45:30Z","markets":[{"key":"h2h","last_update":"2025-07-21T04:45:30Z","outcomes":[{"name":"Greater Western Sydney Giants","price":2.2},{"name":"Western Bulldogs","price":1.67}]}]},{"key":"betfair_ex_au","title":"Betfair","last_update":"2025-07-21T04:45:49Z","markets":[{"key":"h2h","last_update":"2025-07-21T04:45:49Z","outcomes":[{"name":"Greater Western Sydney Giants","price":2.32},{"name":"Western Bulldogs","price":1.68}]},{"key":"h2h_lay","last_update":"2025-07-21T04:45:49Z","outcomes":[{"name":"Greater Western Sydney Giants","price":2.48},{"name":"Western Bulldogs","price":1.76}]}]},{"key":"betfair_ex_uk","title":"Betfair","last_update":"2025-07-21T04:45:31Z","markets":[{"key":"h2h","last_update":"2025-07-21T04:45:31Z","outcomes":[{"name":"Greater Western Sydney Giants","price":2.32},{"name":"Western Bulldogs","price":1.68}]},{"key":"h2h_lay","last_update":"2025-07-21T04:45:31Z","outcomes":[{"name":"Greater Western Sydney Giants","price":2.48},{"name":"Western Bulldogs","price":1.76}]}]},{"key":"betfair_ex_eu","title":"Betfair","last_update":"2025-07-21T04:46:02Z","markets":[{"key":"h2h","last_update":"2025-07-21T04:46:02Z","outcomes":[{"name":"Greater Western Sydney Giants","price":2.32},{"name":"Western Bulldogs","price":1.68}]},{"key":"h2h_lay","last_update":"2025-07-21T04:46:02Z","outcomes":[{"name":"Greater Western Sydney Giants","price":2.48},{"name":"Western Bulldogs","price":1.76}]}]}]},{"id":"f3ef2a581da738f300b1b754f5fb8408","sport_key":"aussierules_afl","sport_title":"AFL","commence_time":"2025-08-01T09:40:38Z","home_team":"Adelaide Crows","away_team":"Hawthorn Hawks","bookmakers":[{"key":"sportsbet","title":"SportsBet","last_update":"2025-07-21T04:46:13Z","markets":[{"key":"h2h","last_update":"2025-07-21T04:46:13Z","outcomes":[{"name":"Adelaide Crows","price":1.47},{"name":"Hawthorn Hawks","price":2.71}]}]},{"key":"paddypower","title":"Paddy Power","last_update":"2025-07-21T04:45:30Z","markets":[{"key":"h2h","last_update":"2025-07-21T04:45:30Z","outcomes":[{"name":"Adelaide Crows","price":1.5},{"name":"Hawthorn Hawks","price":2.62}]}]},{"key":"betfair_ex_uk","title":"Betfair","last_update":"2025-07-21T04:45:31Z","markets":[{"key":"h2h","last_update":"2025-07-21T04:45:31Z","outcomes":[{"name":"Adelaide Crows","price":1.5},{"name":"Hawthorn Hawks","price":2.78}]},{"key":"h2h_lay","last_update":"2025-07-21T04:45:31Z","outcomes":[{"name":"Adelaide Crows","price":1.57},{"name":"Hawthorn Hawks","price":3}]}]},{"key":"betfair_ex_eu","title":"Betfair","last_update":"2025-07-21T04:46:02Z","markets":[{"key":"h2h","last_update":"2025-07-21T04:46:02Z","outcomes":[{"name":"Adelaide Crows","price":1.5},{"name":"Hawthorn Hawks","price":2.78}]},{"key":"h2h_lay","last_update":"2025-07-21T04:46:02Z","outcomes":[{"name":"Adelaide Crows","price":1.57},{"name":"Hawthorn Hawks","price":3}]}]},{"key":"betfair_ex_au","title":"Betfair","last_update":"2025-07-21T04:45:49Z","markets":[{"key":"h2h","last_update":"2025-07-21T04:45:49Z","outcomes":[{"name":"Adelaide Crows","price":1.5},{"name":"Hawthorn Hawks","price":2.78}]},{"key":"h2h_lay","last_update":"2025-07-21T04:45:49Z","outcomes":[{"name":"Adelaide Crows","price":1.57},{"name":"Hawthorn Hawks","price":3}]}]}]},{"id":"97babde9fd2a76d61de71876ecbcc20d","sport_key":"aussierules_afl","sport_title":"AFL","commence_time":"2025-08-02T03:20:49Z","home_team":"Melbourne Demons","away_team":"West Coast Eagles","bookmakers":[{"key":"sportsbet","title":"SportsBet","last_update":"2025-07-21T04:46:13Z","markets":[{"key":"h2h","last_update":"2025-07-21T04:46:13Z","outcomes":[{"name":"Melbourne Demons","price":1.1},{"name":"West Coast Eagles","price":7}]}]},{"key":"paddypower","title":"Paddy Power","last_update":"2025-07-21T04:45:30Z","markets":[{"key":"h2h","last_update":"2025-07-21T04:45:30Z","outcomes":[{"name":"Melbourne Demons","price":1.11},{"name":"West Coast Eagles","price":6.5}]}]},{"key":"betfair_ex_uk","title":"Betfair","last_update":"2025-07-21T04:45:31Z","markets":[{"key":"h2h","last_update":"2025-07-21T04:45:31Z","outcomes":[{"name":"Melbourne Demons","price":1.14},{"name":"West Coast Eagles","price":6.8}]},{"key":"h2h_lay","last_update":"2025-07-21T04:45:31Z","outcomes":[{"name":"Melbourne Demons","price":1.17},{"name":"West Coast Eagles","price":8.2}]}]},{"key":"betfair_ex_au","title":"Betfair","last_update":"2025-07-21T04:45:49Z","markets":[{"key":"h2h","last_update":"2025-07-21T04:45:49Z","outcomes":[{"name":"Melbourne Demons","price":1.14},{"name":"West Coast Eagles","price":6.8}]},{"key":"h2h_lay","last_update":"2025-07-21T04:45:49Z","outcomes":[{"name":"Melbourne Demons","price":1.17},{"name":"West Coast Eagles","price":8.2}]}]},{"key":"betfair_ex_eu","title":"Betfair","last_update":"2025-07-21T04:46:02Z","markets":[{"key":"h2h","last_update":"2025-07-21T04:46:02Z","outcomes":[{"name":"Melbourne Demons","price":1.14},{"name":"West Coast Eagles","price":6.8}]},{"key":"h2h_lay","last_update":"2025-07-21T04:46:02Z","outcomes":[{"name":"Melbourne Demons","price":1.17},{"name":"West Coast Eagles","price":8.2}]}]}]},{"id":"589462df189b38ff51181f76294c18f5","sport_key":"aussierules_afl","sport_title":"AFL","commence_time":"2025-08-02T06:10:50Z","home_team":"Gold Coast Suns","away_team":"Richmond Tigers","bookmakers":[{"key":"sportsbet","title":"SportsBet","last_update":"2025-07-21T04:46:13Z","markets":[{"key":"h2h","last_update":"2025-07-21T04:46:13Z","outcomes":[{"name":"Gold Coast Suns","price":1.08},{"name":"Richmond Tigers","price":8}]}]},{"key":"paddypower","title":"Paddy Power","last_update":"2025-07-21T04:45:30Z","markets":[{"key":"h2h","last_update":"2025-07-21T04:45:30Z","outcomes":[{"name":"Gold Coast Suns","price":1.1},{"name":"Richmond Tigers","price":7}]}]},{"key":"betfair_ex_uk","title":"Betfair","last_update":"2025-07-21T04:45:31Z","markets":[{"key":"h2h","last_update":"2025-07-21T04:45:31Z","outcomes":[{"name":"Gold Coast Suns","price":1.12},{"name":"Richmond Tigers","price":7.8}]},{"key":"h2h_lay","last_update":"2025-07-21T04:45:31Z","outcomes":[{"name":"Gold Coast Suns","price":1.14},{"name":"Richmond Tigers","price":9.4}]}]},{"key":"betfair_ex_au","title":"Betfair","last_update":"2025-07-21T04:45:49Z","markets":[{"key":"h2h","last_update":"2025-07-21T04:45:49Z","outcomes":[{"name":"Gold Coast Suns","price":1.12},{"name":"Richmond Tigers","price":7.8}]},{"key":"h2h_lay","last_update":"2025-07-21T04:45:49Z","outcomes":[{"name":"Gold Coast Suns","price":1.14},{"name":"Richmond Tigers","price":9.4}]}]},{"key":"betfair_ex_eu","title":"Betfair","last_update":"2025-07-21T04:46:02Z","markets":[{"key":"h2h","last_update":"2025-07-21T04:46:02Z","outcomes":[{"name":"Gold Coast Suns","price":1.12},{"name":"Richmond Tigers","price":7.8}]},{"key":"h2h_lay","last_update":"2025-07-21T04:46:02Z","outcomes":[{"name":"Gold Coast Suns","price":1.14},{"name":"Richmond Tigers","price":9.4}]}]}]},{"id":"7a838a8cf4e08a5025be5dc81ecc2621","sport_key":"aussierules_afl","sport_title":"AFL","commence_time":"2025-08-02T06:15:53Z","home_team":"Sydney Swans","away_team":"Essendon Bombers","bookmakers":[{"key":"sportsbet","title":"SportsBet","last_update":"2025-07-21T04:46:13Z","markets":[{"key":"h2h","last_update":"2025-07-21T04:46:13Z","outcomes":[{"name":"Essendon Bombers","price":11},{"name":"Sydney Swans","price":1.04}]}]},{"key":"paddypower","title":"Paddy Power","last_update":"2025-07-21T04:45:30Z","markets":[{"key":"h2h","last_update":"2025-07-21T04:45:30Z","outcomes":[{"name":"Essendon Bombers","price":9},{"name":"Sydney Swans","price":1.05}]}]},{"key":"betfair_ex_au","title":"Betfair","last_update":"2025-07-21T04:45:49Z","markets":[{"key":"h2h","last_update":"2025-07-21T04:45:49Z","outcomes":[{"name":"Essendon Bombers","price":1.01},{"name":"Sydney Swans","price":1.08}]},{"key":"h2h_lay","last_update":"2025-07-21T04:45:49Z","outcomes":[{"name":"Essendon Bombers","price":13.5},{"name":"Sydney Swans","price":1.11}]}]},{"key":"betfair_ex_eu","title":"Betfair","last_update":"2025-07-21T04:46:02Z","markets":[{"key":"h2h","last_update":"2025-07-21T04:46:02Z","outcomes":[{"name":"Essendon Bombers","price":10},{"name":"Sydney Swans","price":1.08}]},{"key":"h2h_lay","last_update":"2025-07-21T04:46:02Z","outcomes":[{"name":"Essendon Bombers","price":13.5},{"name":"Sydney Swans","price":1.11}]}]},{"key":"betfair_ex_uk","title":"Betfair","last_update":"2025-07-21T04:45:31Z","markets":[{"key":"h2h","last_update":"2025-07-21T04:45:31Z","outcomes":[{"name":"Essendon Bombers","price":10},{"name":"Sydney Swans","price":1.08}]},{"key":"h2h_lay","last_update":"2025-07-21T04:45:31Z","outcomes":[{"name":"Essendon Bombers","price":13.5},{"name":"Sydney Swans","price":1.11}]}]}]},{"id":"69944ec277d7bce9ecaf9102167a28c7","sport_key":"aussierules_afl","sport_title":"AFL","commence_time":"2025-08-02T09:35:13Z","home_team":"Collingwood Magpies","away_team":"Brisbane Lions","bookmakers":[{"key":"sportsbet","title":"SportsBet","last_update":"2025-07-21T04:46:13Z","markets":[{"key":"h2h","last_update":"2025-07-21T04:46:13Z","outcomes":[{"name":"Brisbane Lions","price":2.26},{"name":"Collingwood Magpies","price":1.64}]}]},{"key":"paddypower","title":"Paddy Power","last_update":"2025-07-21T04:45:30Z","markets":[{"key":"h2h","last_update":"2025-07-21T04:45:30Z","outcomes":[{"name":"Brisbane Lions","price":2.2},{"name":"Collingwood Magpies","price":1.67}]}]},{"key":"betfair_ex_uk","title":"Betfair","last_update":"2025-07-21T04:45:31Z","markets":[{"key":"h2h","last_update":"2025-07-21T04:45:31Z","outcomes":[{"name":"Brisbane Lions","price":2.32},{"name":"Collingwood Magpies","price":1.68}]},{"key":"h2h_lay","last_update":"2025-07-21T04:45:31Z","outcomes":[{"name":"Brisbane Lions","price":2.48},{"name":"Collingwood Magpies","price":1.76}]}]},{"key":"betfair_ex_eu","title":"Betfair","last_update":"2025-07-21T04:46:02Z","markets":[{"key":"h2h","last_update":"2025-07-21T04:46:02Z","outcomes":[{"name":"Brisbane Lions","price":2.32},{"name":"Collingwood Magpies","price":1.68}]},{"key":"h2h_lay","last_update":"2025-07-21T04:46:02Z","outcomes":[{"name":"Brisbane Lions","price":2.48},{"name":"Collingwood Magpies","price":1.76}]}]},{"key":"betfair_ex_au","title":"Betfair","last_update":"2025-07-21T04:45:49Z","markets":[{"key":"h2h","last_update":"2025-07-21T04:45:49Z","outcomes":[{"name":"Brisbane Lions","price":2.32},{"name":"Collingwood Magpies","price":1.68}]},{"key":"h2h_lay","last_update":"2025-07-21T04:45:49Z","outcomes":[{"name":"Brisbane Lions","price":2.48},{"name":"Collingwood Magpies","price":1.76}]}]}]},{"id":"c7ab6b906fd83fd9bf8c7aa60b27c275","sport_key":"aussierules_afl","sport_title":"AFL","commence_time":"2025-08-03T03:40:45Z","home_team":"St Kilda Saints","away_team":"North Melbourne Kangaroos","bookmakers":[{"key":"sportsbet","title":"SportsBet","last_update":"2025-07-21T04:46:13Z","markets":[{"key":"h2h","last_update":"2025-07-21T04:46:13Z","outcomes":[{"name":"North Melbourne Kangaroos","price":3.02},{"name":"St Kilda Saints","price":1.39}]}]},{"key":"paddypower","title":"Paddy Power","last_update":"2025-07-21T04:45:30Z","markets":[{"key":"h2h","last_update":"2025-07-21T04:45:30Z","outcomes":[{"name":"North Melbourne Kangaroos","price":2.88},{"name":"St Kilda Saints","price":1.4}]}]},{"key":"betfair_ex_au","title":"Betfair","last_update":"2025-07-21T04:45:49Z","markets":[{"key":"h2h","last_update":"2025-07-21T04:45:49Z","outcomes":[{"name":"North Melbourne Kangaroos","price":3.1},{"name":"St Kilda Saints","price":1.42}]},{"key":"h2h_lay","last_update":"2025-07-21T04:45:49Z","outcomes":[{"name":"North Melbourne Kangaroos","price":3.4},{"name":"St Kilda Saints","price":1.48}]}]},{"key":"betfair_ex_uk","title":"Betfair","last_update":"2025-07-21T04:45:31Z","markets":[{"key":"h2h","last_update":"2025-07-21T04:45:31Z","outcomes":[{"name":"North Melbourne Kangaroos","price":3.1},{"name":"St Kilda Saints","price":1.42}]},{"key":"h2h_lay","last_update":"2025-07-21T04:45:31Z","outcomes":[{"name":"North Melbourne Kangaroos","price":3.4},{"name":"St Kilda Saints","price":1.48}]}]},{"key":"betfair_ex_eu","title":"Betfair","last_update":"2025-07-21T04:46:02Z","markets":[{"key":"h2h","last_update":"2025-07-21T04:46:02Z","outcomes":[{"name":"North Melbourne Kangaroos","price":3.1},{"name":"St Kilda Saints","price":1.42}]},{"key":"h2h_lay","last_update":"2025-07-21T04:46:02Z","outcomes":[{"name":"North Melbourne Kangaroos","price":3.4},{"name":"St Kilda Saints","price":1.48}]}]}]},{"id":"abefba6119afaf6168fbf730bb397557","sport_key":"aussierules_afl","sport_title":"AFL","commence_time":"2025-08-03T05:15:20Z","home_team":"Geelong Cats","away_team":"Port Adelaide Power","bookmakers":[{"key":"sportsbet","title":"SportsBet","last_update":"2025-07-21T04:46:13Z","markets":[{"key":"h2h","last_update":"2025-07-21T04:46:13Z","outcomes":[{"name":"Geelong Cats","price":1.16},{"name":"Port Adelaide Power","price":5.3}]}]},{"key":"paddypower","title":"Paddy Power","last_update":"2025-07-21T04:45:30Z","markets":[{"key":"h2h","last_update":"2025-07-21T04:45:30Z","outcomes":[{"name":"Geelong Cats","price":1.17},{"name":"Port Adelaide Power","price":5}]}]},{"key":"betfair_ex_uk","title":"Betfair","last_update":"2025-07-21T04:45:31Z","markets":[{"key":"h2h","last_update":"2025-07-21T04:45:31Z","outcomes":[{"name":"Geelong Cats","price":1.2},{"name":"Port Adelaide Power","price":5.5}]},{"key":"h2h_lay","last_update":"2025-07-21T04:45:31Z","outcomes":[{"name":"Geelong Cats","price":1.23},{"name":"Port Adelaide Power","price":6}]}]},{"key":"betfair_ex_eu","title":"Betfair","last_update":"2025-07-21T04:46:02Z","markets":[{"key":"h2h","last_update":"2025-07-21T04:46:02Z","outcomes":[{"name":"Geelong Cats","price":1.2},{"name":"Port Adelaide Power","price":5.5}]},{"key":"h2h_lay","last_update":"2025-07-21T04:46:02Z","outcomes":[{"name":"Geelong Cats","price":1.23},{"name":"Port Adelaide Power","price":6}]}]},{"key":"betfair_ex_au","title":"Betfair","last_update":"2025-07-21T04:45:49Z","markets":[{"key":"h2h","last_update":"2025-07-21T04:45:49Z","outcomes":[{"name":"Geelong Cats","price":1.2},{"name":"Port Adelaide Power","price":5.5}]},{"key":"h2h_lay","last_update":"2025-07-21T04:45:49Z","outcomes":[{"name":"Geelong Cats","price":1.23},{"name":"Port Adelaide Power","price":6}]}]}]},{"id":"7568aab6e5c3c774a2f4c80c299a78b6","sport_key":"aussierules_afl","sport_title":"AFL","commence_time":"2025-08-03T07:10:35Z","home_team":"Fremantle Dockers","away_team":"Carlton Blues","bookmakers":[{"key":"sportsbet","title":"SportsBet","last_update":"2025-07-21T04:46:13Z","markets":[{"key":"h2h","last_update":"2025-07-21T04:46:13Z","outcomes":[{"name":"Carlton Blues","price":4.2},{"name":"Fremantle Dockers","price":1.23}]}]},{"key":"paddypower","title":"Paddy Power","last_update":"2025-07-21T04:45:30Z","markets":[{"key":"h2h","last_update":"2025-07-21T04:45:30Z","outcomes":[{"name":"Carlton Blues","price":3.75},{"name":"Fremantle Dockers","price":1.25}]}]},{"key":"betfair_ex_au","title":"Betfair","last_update":"2025-07-21T04:45:49Z","markets":[{"key":"h2h","last_update":"2025-07-21T04:45:49Z","outcomes":[{"name":"Carlton Blues","price":4.3},{"name":"Fremantle Dockers","price":1.26}]},{"key":"h2h_lay","last_update":"2025-07-21T04:45:49Z","outcomes":[{"name":"Carlton Blues","price":4.9},{"name":"Fremantle Dockers","price":1.31}]}]},{"key":"betfair_ex_uk","title":"Betfair","last_update":"2025-07-21T04:45:31Z","markets":[{"key":"h2h","last_update":"2025-07-21T04:45:31Z","outcomes":[{"name":"Carlton Blues","price":4.3},{"name":"Fremantle Dockers","price":1.26}]},{"key":"h2h_lay","last_update":"2025-07-21T04:45:31Z","outcomes":[{"name":"Carlton Blues","price":4.9},{"name":"Fremantle Dockers","price":1.31}]}]},{"key":"betfair_ex_eu","title":"Betfair","last_update":"2025-07-21T04:46:02Z","markets":[{"key":"h2h","last_update":"2025-07-21T04:46:02Z","outcomes":[{"name":"Carlton Blues","price":4.3},{"name":"Fremantle Dockers","price":1.26}]},{"key":"h2h_lay","last_update":"2025-07-21T04:46:02Z","outcomes":[{"name":"Carlton Blues","price":4.9},{"name":"Fremantle Dockers","price":1.31}]}]}]}]}